{
  "Patient": [
    {
      "lastMiddleName": "Nguyễn Văn",
      "firstName": "Nguyên",
      "gender": "Nam",
      "height": "165",
      "weight": "55",
      "phoneNum": "0931234567",
      "email": "nguyenvana@gmail.com",
      "citizenID": "911034398097",
      "dateOfBirth": "11-12-2002",
      "address": "435 Điện Biên Phủ, phường 11, quận 1, thành phố Hồ Chí Minh",
      "hometown": "Triệu Đại, Triệu Phong, Quảng Trị",
      "treatProcess": [
        {
          "dateBegin": "01-04-2024",
          "dateEnd": "02-04-2024",
          "timeBegin": "07:00",
          "timeEnd": "08:30",
          "room": "H3-102",
          "title": "Truyền máu",
          "description": "Bệnh nhân đã được thực hiện quá trình truyền máu nhằm cung cấp máu mới và khắc phục tình trạng thiếu máu. Loại máu được sử dụng trong quá trình truyền là máu loại A+. Đã truyền tổng cộng 2 đơn vị máu cho bệnh nhân.",
          "medicalStaffID": "1",
          "id": 1
        },
        {
          "dateBegin": "10-04-2024",
          "dateEnd": "11-04-2024",
          "timeBegin": "08:15",
          "timeEnd": "09:45",
          "room": "H3-102",
          "title": "Phẫu thuật Gan",
          "description": "Sắp tiến hành",
          "medicalStaffID": "1",
          "id": 2
        },
        {
          "dateBegin": "10-03-2024",
          "dateEnd": "11-03-2024",
          "timeBegin": "09:30",
          "timeEnd": "11:00",
          "room": "H1-101",
          "title": "Khám tổng quát và bổ sung thuốc",
          "description": "bệnh nhân đã được tiến hành khám tổng quát và bổ sung thuốc. Trong quá trình khám, bác sĩ đã kiểm tra các chỉ số y tế quan trọng của bệnh nhân như huyết áp, nhịp tim, nhiệt độ cơ thể và đánh giá tổng quan về tình trạng sức khỏe đồng thời bổ sung thuốc theo chỉ định của bác sĩ và theo dõi tình trạng",
          "medicalStaffID": "1",
          "id": 3
        },
        {
          "title": "Xét nghiệm máu",
          "description": "Chỉ số hồng cầu và bạch cầu trong phạm vi bình thường, hemoglobin và hematocrit thấp hơn so với giới hạn bình thường, các thông số MCV, MCH và MCHC nằm trong khoảng bình thường",
          "room": "H3-101",
          "dateBegin": "10-03-2024",
          "dateEnd": "10-03-2024",
          "timeBegin": "10:45",
          "timeEnd": "12:30",
          "medicalStaffID": "1",
          "id": 4
        },
        {
          "title": "Xét nghiệm nước tiểu",
          "description": "ai đo gpt dùm với",
          "room": "H3-101",
          "dateBegin": "10-03-2024",
          "dateEnd": "10-03-2024",
          "timeBegin": "12:00",
          "timeEnd": "13:45",
          "medicalStaffID": "1",
          "id": 5
        }
      ],
      "medHistory": "Từng bị trĩ",
      "symptoms": "Suy nhược cơ thể",
      "diagnosis": "Thiếu máu, xơ gan",
      "id": 1,
      "bloodType": "A",
      "job": "Lập trình viên",
      "lastMidleName": "Nguyễn Văn"
    },
    {
      "id": 2,
      "citizenID": "841471188467",
      "firstName": "Hưng",
      "lastMiddleName": "Bùi Phú",
      "address": "435 Điện Biên Phủ, phường 11, quận 1, thành phố Hồ Chí Minh",
      "gender": "Nam",
      "dateOfBirth": "29-10-1994",
      "height": "172",
      "weight": "60",
      "email": "hung.buiphu123@gmail.com",
      "phoneNum": "0963 789 012",
      "hometown": "Quảng Phong, Cửa Lò, Nghệ An",
      "job": "Lập trình viên",
      "Doctor_ID ": "",
      "medHistory": "Không có",
      "symptoms": "Thường xuyên chóng mặt",
      "diagnosis": "Thiếu máu, xơ gan",
      "treatProcess": [
        {
          "dateBegin": "05-04-2024",
          "dateEnd": "06-04-2024",
          "timeBegin": "07:00",
          "timeEnd": "08:30",
          "room": "H3-102",
          "title": "Kiểm tra EKG",
          "description": "Lịch kiểm tra điện tâm đồ được đặt cho bệnh nhân để đánh giá chức năng tim.",
          "medicalStaffID": "2",
          "id": 1
        }
      ],
      "bloodType": "O"
    },
    {
      "id": 3,
      "citizenID": "470704891087",
      "firstName": "An",
      "lastMiddleName": "Phạm Xuân",
      "address": "435 Điện Biên Phủ, phường 11, quận 1, thành phố Hồ Chí Minh",
      "gender": "Nữ",
      "dateOfBirth": "05-02-1986",
      "height": "160",
      "weight": "50",
      "email": "an.phamxuam86@gmail.com",
      "phoneNum": "0912 345 678",
      "hometown": "Phước Hưng, Vị Thanh, Hậu Giang",
      "job": "Lập trình viên",
      "Doctor_ID ": "",
      "medHistory": "Không có",
      "symptoms": "Đau vùng thái dương trái",
      "diagnosis": "Thiếu máu, xơ gan",
      "treatProcess": [
        {
          "dateBegin": "12-04-2024",
          "dateEnd": "13-04-2024",
          "timeBegin": "08:15",
          "timeEnd": "09:45",
          "room": "H3-102",
          "title": "Phiên tập vận hành",
          "description": "Phiên tập vận hành đã được lên lịch để phục hồi chức năng.",
          "medicalStaffID": "2",
          "id": 1
        }
      ],
      "bloodType": "A"
    },
    {
      "id": 4,
      "citizenID": "071292392595",
      "firstName": "Thành",
      "lastMiddleName": "Phó Tuấn",
      "address": "435 Điện Biên Phủ, phường 11, quận 1, thành phố Hồ Chí Minh",
      "gender": "Nam",
      "dateOfBirth": "20-11-1990",
      "height": "168",
      "weight": "58",
      "email": "thanh.photuan@gmail.com",
      "phoneNum": "0908 456 789",
      "hometown": "Hồng Kỳ, Bến Lức, Long An",
      "job": "Lập trình viên",
      "Doctor_ID ": "#N-A",
      "medHistory": "Không có",
      "symptoms": "Cảm giác đau hoặc nặng ở phía dưới bụng",
      "diagnosis": "Thiếu máu, xơ gan",
      "treatProcess": [
        {
          "dateBegin": "15-04-2024",
          "dateEnd": "16-04-2024",
          "timeBegin": "09:30",
          "timeEnd": "11:00",
          "room": "H1-101",
          "title": "Tư vấn dinh dưỡng",
          "description": "Cuộc hẹn với chuyên gia dinh dưỡng để hướng dẫn và đánh giá chế độ dinh dưỡng.",
          "medicalStaffID": "3",
          "id": 1
        },
        {
          "dateBegin": "20-04-2024",
          "dateEnd": "21-04-2024",
          "timeBegin": "10:45",
          "timeEnd": "12:30",
          "room": "H3-101",
          "title": "Quét MRI",
          "description": "Cuộc hẹn quét MRI được lên lịch để có hình ảnh chi tiết về các cơ quan nội tạng.",
          "medicalStaffID": "3",
          "id": 2
        }
      ],
      "bloodType": "AB"
    },
    {
      "id": 5,
      "citizenID": "829329507883",
      "firstName": "Thành",
      "lastMiddleName": "Phó Tuấn",
      "address": "435 Điện Biên Phủ, phường 11, quận 1, thành phố Hồ Chí Minh",
      "gender": "Nam",
      "dateOfBirth": "20-11-1990",
      "height": "175",
      "weight": "65",
      "email": "thanh.photuan@gmail.com",
      "phoneNum": "0908 456 789",
      "hometown": "Phú Điền, Phú Vang, Thừa Thiên Huế",
      "job": "Lập trình viên",
      "Doctor_ID ": "",
      "medHistory": "Thoái hóa đốt sống",
      "symptoms": "Ổn định",
      "diagnosis": "Thiếu máu, xơ gan",
      "treatProcess": [
        {
          "dateBegin": "25-04-2024",
          "dateEnd": "26-04-2024",
          "timeBegin": "12:00",
          "timeEnd": "13:45",
          "room": "H3-101",
          "title": "Khám siêu âm",
          "description": "Cuộc hẹn siêu âm để chẩn đoán mục đích.",
          "medicalStaffID": "3",
          "id": 1
        }
      ],
      "bloodType": "B"
    },
    {
      "id": 6,
      "citizenID": "618797017311",
      "firstName": "Thanh",
      "lastMiddleName": "Hoàng Văn",
      "address": "435 Điện Biên Phủ, phường 11, quận 1, thành phố Hồ Chí Minh",
      "gender": "Nam",
      "dateOfBirth": "27-04-1993",
      "height": "158",
      "weight": "48",
      "email": "thanh.hoangvan@gmail.com",
      "phoneNum": "0921 234 567",
      "hometown": "Bình Yên, Lập Thạch, Vĩnh Phúc",
      "job": "Lập trình viên",
      "Doctor_ID ": "",
      "medHistory": "Không có",
      "symptoms": "Tiểu chảy",
      "diagnosis": "Thiếu máu, xơ gan",
      "treatProcess": [
        {
          "dateBegin": "30-04-2024",
          "dateEnd": "01-05-2024",
          "timeBegin": "07:30",
          "timeEnd": "09:15",
          "room": "H3-102",
          "title": "Phiên tập nghề nghiệp",
          "description": "Phiên tập nghề nghiệp đã được lên lịch để phục hồi chức năng.",
          "medicalStaffID": "4",
          "id": 1
        },
        {
          "dateBegin": "05-05-2024",
          "dateEnd": "06-05-2024",
          "timeBegin": "09:00",
          "timeEnd": "10:30",
          "room": "H1-101",
          "title": "Kiểm tra nha khoa",
          "description": "Cuộc hẹn kiểm tra nha khoa định kỳ để đánh giá sức khỏe miệng.",
          "medicalStaffID": "4",
          "id": 2
        }
      ],
      "bloodType": "O"
    },
    {
      "id": 7,
      "citizenID": "164171815965",
      "firstName": "Hà",
      "lastMiddleName": "Nguyễn Thị Thu",
      "address": "435 Điện Biên Phủ, phường 11, quận 1, thành phố Hồ Chí Minh",
      "gender": "Nữ",
      "dateOfBirth": "10-02-1978",
      "height": "170",
      "weight": "62",
      "email": "ha.nguyenthithu@gmail.com",
      "phoneNum": "0998 765 432",
      "hometown": "Đắk Phú, Đắk Tô, Kon Tum",
      "job": "Lập trình viên",
      "Doctor_ID ": "",
      "medHistory": "Không có",
      "symptoms": "Tầm nhìn kém",
      "diagnosis": "Thiếu máu, xơ gan",
      "treatProcess": [
        {
          "dateBegin": "10-05-2024",
          "dateEnd": "11-05-2024",
          "timeBegin": "10:15",
          "timeEnd": "11:45",
          "room": "H3-102",
          "title": "Phiên tập nói",
          "description": "Phiên tập nói đã được lên lịch để phục hồi chức năng ngôn ngữ.",
          "medicalStaffID": "4",
          "id": 1
        },
        {
          "dateBegin": "15-05-2024",
          "dateEnd": "16-05-2024",
          "timeBegin": "12:30",
          "timeEnd": "14:15",
          "room": "H3-101",
          "title": "Đánh giá tình trạng trí óc",
          "description": "Cuộc hẹn để đánh giá và đánh giá chức năng trí óc.",
          "medicalStaffID": "5",
          "id": 2
        }
      ],
      "bloodType": "A"
    },
    {
      "id": 8,
      "citizenID": "529785803689",
      "firstName": "Dũng",
      "lastMiddleName": "Trần Văn",
      "address": "435 Điện Biên Phủ, phường 11, quận 1, thành phố Hồ Chí Minh",
      "gender": "Nam",
      "dateOfBirth": "14-02-1989",
      "height": "163",
      "weight": "56",
      "email": "dung.tranvan@gmail.com",
      "phoneNum": "0963 789 012",
      "hometown": "Hòa Thạch, Phú Thọ, Phú Thọ",
      "job": "Lập trình viên",
      "Doctor_ID ": "",
      "medHistory": "Không có",
      "symptoms": "Sốt",
      "diagnosis": "Thiếu máu, xơ gan",
      "treatProcess": [
        {
          "dateBegin": "20-05-2024",
          "dateEnd": "21-05-2024",
          "timeBegin": "13:45",
          "timeEnd": "15:30",
          "room": "H3-101",
          "title": "Tư vấn di truyền học",
          "description": "Cuộc hẹn để tư vấn di truyền học và đánh giá rủi ro.",
          "medicalStaffID": "5",
          "id": 1
        }
      ],
      "bloodType": "AB"
    },
    {
      "id": 9,
      "citizenID": "714698464496",
      "firstName": "Hương",
      "lastMiddleName": "Lê Thị",
      "address": "435 Điện Biên Phủ, phường 11, quận 1, thành phố Hồ Chí Minh",
      "gender": "Nữ",
      "dateOfBirth": "12-05-1982",
      "height": "167",
      "weight": "59",
      "email": "huong.lethi@gmail.com",
      "phoneNum": "0978 654 321",
      "hometown": "Bảo Tân, Lục Ngạn, Bắc Giang",
      "job": "Lập trình viên",
      "Doctor_ID ": "",
      "medHistory": "Không có",
      "symptoms": "Mệt mỏi, uể oải",
      "diagnosis": "Thiếu máu, xơ gan",
      "treatProcess": [
        {
          "dateBegin": "25-05-2024",
          "dateEnd": "26-05-2024",
          "timeBegin": "15:00",
          "timeEnd": "16:45",
          "room": "H3-101",
          "title": "Kiểm tra mắt",
          "description": "Cuộc hẹn để kiểm tra mắt và kiểm tra thị lực chi tiết.",
          "medicalStaffID": "5",
          "id": 1
        }
      ],
      "bloodType": "B"
    },
    {
      "id": 10,
      "citizenID": "184965740502",
      "firstName": "Tuấn",
      "lastMiddleName": "Hoàng Minh",
      "address": "435 Điện Biên Phủ, phường 11, quận 1, thành phố Hồ Chí Minh",
      "gender": "Nam",
      "dateOfBirth": "18-08-1997",
      "height": "171",
      "weight": "64",
      "email": "tuanhoangminh@gmail.com",
      "phoneNum": "0945 321 678",
      "hometown": "Vĩnh Hải, Ninh Hải, Ninh Thuận",
      "job": "Lập trình viên",
      "Doctor_ID ": "",
      "medHistory": "Không có",
      "symptoms": "Thường xuyên chóng mặt",
      "diagnosis": "Thiếu máu, xơ gan",
      "treatProcess": [
        {
          "dateBegin": "30-05-2024",
          "dateEnd": "31-05-2024",
          "timeBegin": "17:15",
          "timeEnd": "19:00",
          "room": "H3-102",
          "title": "Kiểm tra thính lực",
          "description": "Cuộc hẹn để đánh giá thính lực và kiểm tra thính lực.",
          "medicalStaffID": "6",
          "id": 1
        },
        {
          "dateBegin": "05-06-2024",
          "dateEnd": "06-06-2024",
          "timeBegin": "07:00",
          "timeEnd": "08:30",
          "room": "H3-102",
          "title": "Kiểm tra sức khỏe tổng quát",
          "description": "Cuộc hẹn kiểm tra sức khỏe tổng quát định kỳ cho đánh giá sức khỏe chung.",
          "medicalStaffID": "6",
          "id": 2
        }
      ],
      "bloodType": "B"
    }
  ],
  "MedicalStaff": [
    {
      "id": "1",
      "position": "Bác sĩ",
      "citizenID": "768240953126",
      "firstName": "Anh",
      "lastMiddleName": "Lê Hòa",
      "gender": "Nữ",
      "dateOfBirth": "15-09-1954",
      "email": "lehoaanh@gmail.com",
      "phoneNum": "0931765432",
      "hometown": "Thanh Trạch, Bố Trạch, Quảng Bình",
      "education": [
        {
          "university": "Trường đại học y dược TP HCM",
          "major": "Y khoa",
          "degree": "Cử nhân",
          "id": 1,
          "dateBegin": "20-08-1975",
          "dateEnd": "12-07-1981"
        }
      ],
      "cert": [
        {
          "title": "Chứng chỉ hành nghề",
          "date": "12-12-1982",
          "organization": "Bộ y tế",
          "id": 1
        },
        {
          "title": "chứng chỉ bác sĩ chuyên khoa 1",
          "date": "02-02-1984",
          "organization": "Bộ y tế",
          "id": 2
        },
        {
          "title": "chứng chỉ bác sĩ chuyên khoa 2",
          "date": "03-05-1986",
          "organization": "Bộ y tế",
          "id": 3
        }
      ],
      "specialty": "Tim mạch",
      "schedule": [
        {
          "date": "20-03-2020",
          "timeBegin": "10:30",
          "timeEnd": "12:30",
          "room": "H7-302",
          "title": "Họp",
          "description": "nostrud tempor ex consectetur exercitation eiusmod minim. tempor ex consectetur exercitation eiusmod minim veniam, et ipsum ad consequat. sed elit,. ex consectetur exercitation eiusmod minim. consectetur exercitation eiusmod minim veniam, et ipsum ad consequat. sed. exercitation eiusmod minim veniam, et ipsum."
        },
        {
          "date": "25-03-2024",
          "timeBegin": "10:30",
          "title": "Điều trị bệnh nhân",
          "timeEnd": "12:30",
          "id": 2,
          "room": "H7-302",
          "description": "nostrud tempor ex consectetur exercitation eiusmod minim. tempor ex consectetur exercitation eiusmod minim veniam, et ipsum ad consequat. sed elit,. ex consectetur exercitation eiusmod minim. consectetur exercitation eiusmod minim veniam, et ipsum ad consequat. sed. exercitation eiusmod minim veniam, et ipsum."
        }
      ],
      "address": "183 Lê Quang Định, phường 9, quận Gò Vấp, thành phố Hồ Chí Minh",
      "lastMidleName": "Lê Hòa"
    },
    {
      "id": "2",
      "position": "Bác sĩ",
      "citizenID": "509431276845",
      "firstName": "Bình",
      "lastMiddleName": "Nguyễn Hòa",
      "gender": "Nam",
      "dateOfBirth": "10-12-1984",
      "email": "nguyenhoabinh@gmail.com",
      "phoneNum": "090345787",
      "hometown": "An Lạc, Phú Xuyên, Hà Nội",
      "education": [
        {
          "university": "Trường đại học Phạm Ngọc Thạch TP HCM",
          "major": "Tuần hoàn",
          "degree": "Thạc sĩ",
          "id": 1,
          "dateBegin": "12-08-2004",
          "dateEnd": "19-07-2012"
        }
      ],
      "cert": [
        {
          "title": "Chứng chỉ hành nghề",
          "date": "12-9-2013",
          "organization": "Bộ y tế",
          "id": 1
        }
      ],
      "specialty": "khoa nội",
      "schedule": [
        {
          "date": "12-04-2024",
          "timeBegin": "00:30",
          "title": "Khám bệnh",
          "timeEnd": "11:30",
          "id": 1,
          "room": "H7-302",
          "description": "incididunt minim Lorem ad laboris. minim Lorem ad laboris commodo ex dolor ut veniam, enim. Lorem ad laboris commodo ex dolor ut. ad laboris commodo ex dolor ut veniam, enim adipiscing elit, nisi do et. laboris commodo ex dolor ut veniam, enim adipiscing elit, nisi do et eiusmod."
        },
        {
          "date": "29-03-2024",
          "timeBegin": "10:30",
          "title": "Đo điện tâm đồ",
          "timeEnd": "12:30",
          "id": 2,
          "room": "H7-302",
          "description": "nostrud commodo amet, veniam, consectetur do. commodo amet, veniam, consectetur do exercitation laboris et eiusmod. amet, veniam, consectetur do exercitation laboris et eiusmod. veniam, consectetur do exercitation laboris et eiusmod tempor quis incididunt elit, consequat. magna. consectetur do exercitation laboris et eiusmod tempor."
        }
      ],
      "address": "183 Lê Quang Định, phường 9, quận Gò Vấp, thành phố Hồ Chí Minh"
    },
    {
      "id": 3,
      "position": "Bác sĩ",
      "citizenID": "623780941526",
      "firstName": "Cường",
      "lastMiddleName": "Trần Quang",
      "gender": "Nam",
      "dateOfBirth": "10-12-1970",
      "email": "tranquangcuong@gmail.com",
      "phoneNum": "0907899087",
      "hometown": "Nam Đồng, Đại Lộc, Quảng Nam",
      "education": [
        {
          "university": "Trường đại học Y dược TP HCM",
          "major": "Tuần hoàn",
          "degree": "Tiến sĩ",
          "id": 1,
          "dateBegin": "12-09-1990",
          "dateEnd": "20-07-1999"
        }
      ],
      "cert": [
        {
          "title": "Chứng chỉ hành nghề",
          "date": "02-09-2000",
          "organization": "Bộ y tế",
          "id": 1
        },
        {
          "title": "Bác sĩ cao cấp (hạng I)",
          "date": "02-09-2008",
          "organization": "Bộ y tế",
          "id": 2
        }
      ],
      "specialty": "khoa nội",
      "schedule": [
        {
          "date": "19-02-2024",
          "timeBegin": "09:00",
          "title": "Xét nghiệm hóa sinh",
          "timeEnd": "21:00",
          "id": 1,
          "room": "H7-302",
          "description": "aliquip aliqua. exercitation ipsum. aliqua. exercitation ipsum tempor commodo consequat. labore consectetur elit,. exercitation ipsum tempor commodo consequat. labore consectetur elit, nostrud ullamco ut. ipsum tempor commodo consequat. labore consectetur elit, nostrud ullamco ut adipiscing veniam, ut. tempor commodo consequat. labore consectetur elit, nostrud ullamco ut adipiscing veniam, ut ex."
        },
        {
          "date": "02-03-2024",
          "timeBegin": "8:30",
          "title": "Hội chuẩn bệnh tim",
          "timeEnd": "04:30",
          "id": 2,
          "room": "H7-302",
          "description": "commodo elit, ea ut. elit, ea ut labore ullamco ex enim consectetur veniam,. ea ut labore ullamco ex enim consectetur veniam, dolore sit minim Ut. ut labore ullamco ex enim consectetur veniam, dolore sit minim Ut nisi. labore ullamco ex enim consectetur veniam,."
        },
        {
          "date": "22-03-2024",
          "timeBegin": "8:30",
          "title": "Điều trị hở van tim",
          "timeEnd": "00:30",
          "id": 3,
          "room": "H7-302",
          "description": "consectetur magna consequat. exercitation minim. magna consequat. exercitation minim. consequat. exercitation minim ut commodo ullamco. exercitation minim ut commodo ullamco quis ut. minim ut commodo ullamco quis ut dolor dolore ea aliquip ipsum sed."
        }
      ],
      "address": "183 Lê Quang Định, phường 9, quận Gò Vấp, thành phố Hồ Chí Minh"
    },
    {
      "id": 4,
      "position": "Bác sĩ",
      "citizenID": "421789056312",
      "firstName": "Dương",
      "lastMiddleName": "Lý",
      "gender": "Nam",
      "dateOfBirth": "10-12-1964",
      "email": "tranduong@gmail.com",
      "phoneNum": "0701238290",
      "hometown": "Trường Sơn, Hương Sơn, Hà Tĩnh",
      "education": [
        {
          "university": "Trường đại học Y Dược Huế",
          "major": "Hô hấp",
          "degree": "Tiến sĩ",
          "id": 1,
          "dateBegin": "02-08-1984",
          "dateEnd": "18-07-1990"
        }
      ],
      "cert": [
        {
          "title": "Chứng chỉ hành nghề",
          "date": "15-09-1991",
          "organization": "Bộ y tế",
          "id": 1
        }
      ],
      "specialty": "khoa tai mũi họng",
      "schedule": [
        {
          "date": "18-03-2024",
          "timeBegin": "09:00",
          "title": "Nội soi tai mũi họng",
          "timeEnd": "11:00",
          "id": 1,
          "room": "H7-302",
          "description": "ad commodo nostrud exercitation magna elit, nisi aliquip ipsum laboris incididunt. commodo nostrud exercitation magna elit, nisi aliquip. nostrud exercitation magna elit, nisi aliquip. exercitation magna elit, nisi aliquip ipsum laboris incididunt ex dolor. magna elit, nisi aliquip ipsum laboris incididunt ex dolor et."
        },
        {
          "date": "21-03-2024",
          "timeBegin": "11:30",
          "title": "Khám bệnh",
          "timeEnd": "13:30",
          "id": 2,
          "room": "H7-302",
          "description": "amet, labore minim elit, magna quis. labore minim elit, magna quis do incididunt commodo consectetur. minim elit, magna quis do incididunt commodo consectetur sit enim ut consequat.. elit, magna quis do incididunt commodo consectetur sit enim ut consequat.. magna quis do incididunt commodo consectetur."
        },
        {
          "date": "29-03-2024",
          "timeBegin": "11:30",
          "title": "Chuẩn đoán và điều trị viêm xoang",
          "timeEnd": "13:30",
          "id": 3,
          "room": "H7-302",
          "description": "labore Lorem et enim elit, amet, ullamco eiusmod ex aliqua.. Lorem et enim elit, amet, ullamco eiusmod. et enim elit, amet, ullamco eiusmod ex aliqua. veniam, ut nisi. enim elit, amet, ullamco eiusmod ex aliqua. veniam,. elit, amet, ullamco eiusmod."
        },
        {
          "date": "12-04-2024",
          "timeBegin": "00:30",
          "title": "Nghỉ phép",
          "timeEnd": "13:30",
          "id": 4,
          "room": "H7-302",
          "description": "incididunt ea sed ut adipiscing veniam, nostrud. ea sed ut adipiscing veniam, nostrud ullamco laboris Ut labore enim ex aliquip. sed ut adipiscing veniam, nostrud ullamco. ut adipiscing veniam, nostrud. adipiscing veniam, nostrud ullamco laboris Ut labore enim ex aliquip ipsum."
        }
      ],
      "address": "183 Lê Quang Định, phường 9, quận Gò Vấp, thành phố Hồ Chí Minh"
    },
    {
      "id": 5,
      "position": "Bác sĩ",
      "citizenID": "879640231576",
      "firstName": "Emily",
      "lastMiddleName": "William",
      "gender": "Nữ",
      "dateOfBirth": "10-02-1979",
      "email": "williamemily@gmail.com",
      "phoneNum": "0907854367",
      "hometown": "Điện Lâm, Điện Bàn, Quảng Nam",
      "education": [
        {
          "university": "Trường Y khoa Yale-Đại học Yale",
          "major": "Da liễu",
          "degree": "Tiến sĩ",
          "id": 1,
          "dateBegin": "15-02-1999",
          "dateEnd": "20-08-2007"
        }
      ],
      "cert": [
        {
          "title": "Chứng chỉ hành nghề",
          "date": "02-09-2008",
          "organization": "Bộ y tế",
          "id": 1
        },
        {
          "title": "Bác sĩ cao cấp (hạng II)",
          "date": "02-09-2010",
          "organization": "Bộ y tế",
          "id": 2
        }
      ],
      "specialty": "khoa Da liễu",
      "schedule": [
        {
          "date": "01-03-2024",
          "timeBegin": "10:00",
          "title": "Xét nghiệm mô tế bào",
          "timeEnd": "03:00",
          "id": 1,
          "room": "H7-302",
          "description": "ad tempor Ut consequat. ut nostrud do ea Lorem labore aliquip. tempor Ut consequat. ut nostrud. Ut consequat. ut nostrud do ea Lorem labore aliquip aliqua.. consequat. ut nostrud do ea Lorem labore. ut nostrud do ea."
        },
        {
          "date": "02-03-2024",
          "timeBegin": "10:30",
          "title": "Hội nghị Da liễu thành phố",
          "timeEnd": "04:30",
          "id": 2,
          "room": "H7-302",
          "description": "labore exercitation ut ipsum Ut ea adipiscing. exercitation ut ipsum Ut ea adipiscing dolore nisi quis ad. ut ipsum Ut ea adipiscing dolore nisi quis ad. ipsum Ut ea adipiscing dolore nisi quis ad elit,. Ut ea adipiscing dolore nisi quis ad elit,."
        },
        {
          "date": "12-03-2024",
          "timeBegin": "8:30",
          "title": "Điều trị chuyên sâu về da liễu",
          "timeEnd": "14:30",
          "id": 3,
          "room": "H7-302",
          "description": "elit, consequat. dolor incididunt et amet,. consequat. dolor incididunt et amet, tempor. dolor incididunt et amet,. incididunt et amet, tempor ut aliquip do labore magna Lorem quis ex sit. et amet, tempor ut aliquip do labore magna Lorem."
        }
      ],
      "address": "183 Lê Quang Định, phường 9, quận Gò Vấp, thành phố Hồ Chí Minh"
    },
    {
      "id": 6,
      "position": "Bác sĩ",
      "citizenID": "305847921634",
      "firstName": "Ferb",
      "lastMiddleName": "Alan",
      "gender": "Nam",
      "dateOfBirth": "10-09-1969",
      "email": "anlanferb@gmail.com",
      "phoneNum": "09317634890",
      "hometown": "Hoà Hội, Hoà Vang, Đà Nẵng",
      "education": [
        {
          "university": "Trường đại học y dược TP HCM",
          "major": "Y đa khoa",
          "degree": "Thạc sĩ",
          "id": 1,
          "dateBegin": "20-08-1988",
          "dateEnd": "12-07-1996"
        }
      ],
      "cert": [
        {
          "title": "Chứng chỉ hành nghề",
          "date": "12-12-1985",
          "organization": "Bộ y tế",
          "id": 1
        }
      ],
      "specialty": "khoa ngoại",
      "schedule": [
        {
          "timeBegin": "09:00",
          "title": "Phẫu thuật nội soi viêm ruột thừa",
          "timeEnd": "04:00",
          "id": 1,
          "date": "02-03-2024",
          "room": "H7-302",
          "description": "ullamco ut aliqua. quis enim. ut aliqua. quis enim ea consectetur exercitation sed veniam, aliquip. aliqua. quis enim ea consectetur exercitation sed veniam, aliquip elit, ut labore. quis enim ea consectetur exercitation sed veniam, aliquip elit, ut. enim ea consectetur exercitation sed veniam, aliquip elit, ut labore nostrud."
        },
        {
          "timeBegin": "10:30",
          "title": "Phẫu thuật cắt túi sỏi mật",
          "timeEnd": "14:30",
          "id": 2,
          "date": "12-03-2024",
          "room": "H7-302",
          "description": "dolore ullamco enim amet, ut et aliqua. incididunt ea veniam, aliquip Ut. ullamco enim amet, ut et aliqua. incididunt ea veniam, aliquip Ut. enim amet, ut et aliqua. incididunt ea. amet, ut et aliqua. incididunt ea veniam, aliquip Ut labore nisi. ut et aliqua. incididunt ea veniam, aliquip Ut labore nisi ad commodo."
        },
        {
          "timeBegin": "10:30",
          "title": "Nội soi bao tử",
          "timeEnd": "23:30",
          "id": 3,
          "date": "21-03-2024",
          "room": "H7-302",
          "description": "minim elit, exercitation ut ullamco et adipiscing ad do Lorem laboris incididunt. elit, exercitation ut ullamco et adipiscing. exercitation ut ullamco et adipiscing ad do. ut ullamco et adipiscing ad do Lorem laboris incididunt veniam,. ullamco et adipiscing ad do Lorem laboris incididunt veniam, magna consectetur Ut nisi."
        }
      ],
      "address": "183 Lê Quang Định, phường 9, quận Gò Vấp, thành phố Hồ Chí Minh"
    },
    {
      "id": 7,
      "position": "Bác sĩ",
      "citizenID": "192487503186",
      "firstName": "Giang",
      "lastMiddleName": "Nguyễn Hương",
      "gender": "Nữ",
      "dateOfBirth": "10-01-1984",
      "email": "nguyenhuonggiang@gmail.com",
      "phoneNum": "0903123487",
      "hometown": "An Lợi, Bình Đại, Bến Tre",
      "education": [
        {
          "university": "Trường đại học Phạm Ngọc Thạch TP HCM",
          "major": "Răng hàm mặt",
          "degree": "Thạc sĩ",
          "id": 1,
          "dateBegin": "01-08-2004",
          "dateEnd": "08-02-2012"
        }
      ],
      "cert": [
        {
          "title": "Chứng chỉ hành nghề",
          "date": "02-08-2013",
          "organization": "Bộ y tế",
          "id": 1
        }
      ],
      "specialty": "khoa răng hàm mặt",
      "schedule": [
        {
          "timeBegin": "08:30",
          "title": "Khám bệnh và tư vấn trồn răng",
          "timeEnd": "17:30",
          "id": 1,
          "date": "15-03-2024",
          "room": "H7-302",
          "description": "dolore magna ullamco commodo tempor adipiscing aliqua. incididunt eiusmod consectetur minim. magna ullamco commodo tempor adipiscing aliqua. incididunt. ullamco commodo tempor adipiscing aliqua. incididunt eiusmod consectetur minim et amet, Lorem. commodo tempor adipiscing aliqua. incididunt eiusmod consectetur minim. tempor adipiscing aliqua. incididunt eiusmod consectetur minim et amet, Lorem dolor sed."
        },
        {
          "timeBegin": "11:30",
          "title": "Trồng răng implant",
          "timeEnd": "Invalid date",
          "id": 2,
          "date": "27-03-2024",
          "room": "H7-302",
          "description": "amet, veniam, Lorem minim dolore. veniam, Lorem minim dolore sit nostrud adipiscing do dolor. Lorem minim dolore sit nostrud adipiscing do dolor. minim dolore sit nostrud adipiscing do dolor Ut commodo sed ad. dolore sit nostrud adipiscing do dolor Ut."
        },
        {
          "timeBegin": "11:30",
          "title": "Trồng răng sứ",
          "timeEnd": "Invalid date",
          "id": 3,
          "date": "29-03-2024",
          "room": "H7-302",
          "description": "Lorem Ut tempor aliquip amet, dolor et adipiscing ad. Ut tempor aliquip amet, dolor et adipiscing ad. tempor aliquip amet, dolor et adipiscing ad quis sit laboris do labore. aliquip amet, dolor et adipiscing ad quis. amet, dolor et adipiscing ad."
        }
      ],
      "address": "183 Lê Quang Định, phường 9, quận Gò Vấp, thành phố Hồ Chí Minh"
    },
    {
      "id": 8,
      "position": "Bác sĩ",
      "citizenID": "536197420815",
      "firstName": "Hòa",
      "lastMiddleName": "Lê",
      "gender": "Nam",
      "dateOfBirth": "01-12-1970",
      "email": "lehoa@gmail.com",
      "phoneNum": "0907908456",
      "hometown": "Lam Đồng, Di Linh, Lâm Đồng",
      "education": [
        {
          "university": "Trường đại học Y dược TP HCM",
          "major": "Kĩ thuật xét nghiệm y học",
          "degree": "Thạc sĩ",
          "id": 1,
          "dateBegin": "10-08-1990",
          "dateEnd": "20-07-1997"
        }
      ],
      "cert": [
        {
          "title": "Chứng chỉ hành nghề",
          "date": "02-09-2000",
          "organization": "Bộ y tế",
          "id": 1
        }
      ],
      "specialty": "khoa Xét nghiệm",
      "schedule": [
        {
          "timeBegin": "09:00",
          "title": "Xét nghiệm huyết học tế bào",
          "timeEnd": "21:00",
          "id": 1,
          "date": "19-03-2024",
          "room": "H7-302",
          "description": "nisi quis enim commodo Lorem adipiscing ut exercitation. quis enim commodo Lorem adipiscing ut exercitation do aliquip dolore ea ex. enim commodo Lorem adipiscing ut exercitation do aliquip. commodo Lorem adipiscing ut. Lorem adipiscing ut exercitation do aliquip dolore ea ex et minim sed nostrud."
        },
        {
          "timeBegin": "8:30",
          "title": "Xét nghiệm sinh hóa đường",
          "timeEnd": "00:30",
          "id": 2,
          "date": "22-03-2024",
          "room": "H7-302",
          "description": "nostrud ut dolore sit Ut dolor. ut dolore sit Ut dolor ut veniam, consequat. commodo ex et exercitation enim. dolore sit Ut dolor ut veniam,. sit Ut dolor ut veniam, consequat. commodo ex et exercitation enim elit, magna. Ut dolor ut veniam, consequat.."
        },
        {
          "timeBegin": "8:30",
          "title": "Xét nghiệm máu",
          "timeEnd": "Invalid date",
          "id": 3,
          "date": "29-03-2024",
          "room": "H7-302",
          "description": "aliquip ullamco enim ex dolor. ullamco enim ex dolor et ipsum Lorem nostrud ut eiusmod elit, ea. enim ex dolor et ipsum Lorem nostrud. ex dolor et ipsum Lorem nostrud ut eiusmod elit, ea aliqua.. dolor et ipsum Lorem nostrud ut eiusmod elit,."
        }
      ],
      "address": "183 Lê Quang Định, phường 9, quận Gò Vấp, thành phố Hồ Chí Minh"
    },
    {
      "id": 9,
      "position": "Bác sĩ",
      "citizenID": "748205913267",
      "firstName": "Yên",
      "lastMiddleName": "Lê Hoàng",
      "gender": "Nữ",
      "dateOfBirth": "10-12-1964",
      "email": "lehoangyen@gmail.com",
      "phoneNum": "0701198790",
      "hometown": "Phước Kiền, Hòa Vang, Đà Nẵng",
      "education": [
        {
          "university": "Trường đại học Y Dược Thai Nguyên",
          "major": "Hộ sinh",
          "degree": "Thạc sĩ",
          "id": 1,
          "dateBegin": "02-08-1984",
          "dateEnd": "18-07-1990"
        }
      ],
      "cert": [
        {
          "title": "Chứng chỉ hành nghề",
          "date": "12-8-1991",
          "organization": "Bộ y tế",
          "id": 1
        },
        {
          "title": "Bác sĩ cao cấp (hạng I)",
          "date": "12-8-1996",
          "organization": "Bộ y tế",
          "id": 2
        }
      ],
      "specialty": "khoa sản",
      "schedule": [
        {
          "timeBegin": "09:00",
          "title": "Chăm sóc thai nghén",
          "timeEnd": "21:00",
          "id": 1,
          "date": "19-03-2024",
          "room": "H7-302",
          "description": "consequat. ipsum quis veniam, minim aliqua. nostrud et ullamco tempor nisi ut dolore. ipsum quis veniam, minim aliqua. nostrud et. quis veniam, minim aliqua. nostrud et ullamco tempor nisi ut dolore ad. veniam, minim aliqua. nostrud et ullamco tempor nisi. minim aliqua. nostrud et ullamco tempor nisi ut dolore ad enim amet, aliquip."
        },
        {
          "timeBegin": "11:30",
          "title": "Chăm sóc khám thai định kì",
          "timeEnd": "00:30",
          "id": 2,
          "date": "22-03-2024",
          "room": "H7-302",
          "description": "ex ad aliquip veniam, minim et sit commodo ut eiusmod ea ipsum Lorem. ad aliquip veniam, minim et sit commodo ut eiusmod ea ipsum. aliquip veniam, minim et sit commodo ut eiusmod ea ipsum Lorem. veniam, minim et sit commodo ut eiusmod ea ipsum Lorem. minim et sit commodo ut eiusmod ea ipsum Lorem incididunt dolor consectetur laboris."
        },
        {
          "timeBegin": "11:30",
          "title": "Chăm sóc khám thai định kì",
          "timeEnd": "Invalid date",
          "id": 3,
          "date": "29-04-2024",
          "room": "H7-302",
          "description": "ullamco quis enim nisi minim nostrud consequat.. quis enim nisi minim nostrud consequat. ex labore. enim nisi minim nostrud. nisi minim nostrud consequat.. minim nostrud consequat. ex labore veniam,."
        }
      ],
      "address": "183 Lê Quang Định, phường 9, quận Gò Vấp, thành phố Hồ Chí Minh"
    },
    {
      "id": 10,
      "position": "Bác sĩ",
      "citizenID": "319672048573",
      "firstName": "Lan",
      "lastMiddleName": "Hoàng Ninh",
      "gender": "Nữ",
      "dateOfBirth": "10-02-1979",
      "email": "hoangninhlan@gmail.com",
      "phoneNum": "0909845367",
      "hometown": "Phước Ninh, Ninh Phước, Ninh Thuận",
      "education": [
        {
          "university": "Trường Y khoa Hà Nội",
          "major": "Y học cổ truyền",
          "degree": "Tiến sĩ",
          "id": 1,
          "dateBegin": "15-04-1999",
          "dateEnd": "29-08-2007"
        }
      ],
      "cert": [
        {
          "title": "Chứng chỉ hành nghề",
          "date": "02-09-2008",
          "organization": "Bộ y tế",
          "id": 1
        }
      ],
      "specialty": "khoa Y học cổ truyền",
      "schedule": [
        {
          "timeBegin": "10:00",
          "title": "Châm cứu tứ chi",
          "timeEnd": "21:00",
          "id": 1,
          "date": "19-02-2024",
          "room": "H7-302",
          "description": "dolor veniam, Lorem et labore adipiscing consectetur eiusmod amet, nostrud. veniam, Lorem et labore adipiscing consectetur eiusmod amet, nostrud laboris enim Ut. Lorem et labore adipiscing consectetur eiusmod amet,. et labore adipiscing consectetur eiusmod amet, nostrud laboris. labore adipiscing consectetur eiusmod amet, nostrud laboris enim Ut."
        },
        {
          "timeBegin": "10:30",
          "title": "Hồi phục sau chấn thương",
          "timeEnd": "14:30",
          "id": 2,
          "date": "12-03-2024",
          "room": "H7-302",
          "description": "et incididunt enim laboris tempor ex. incididunt enim laboris tempor ex eiusmod veniam, ut aliquip commodo consequat.. enim laboris tempor ex eiusmod veniam,. laboris tempor ex eiusmod veniam, ut. tempor ex eiusmod veniam, ut aliquip commodo consequat. nisi Ut exercitation sed sit."
        },
        {
          "timeBegin": "10:30",
          "title": "Khám và điều trị",
          "timeEnd": "14:30",
          "id": 3,
          "date": "12-04-2024",
          "room": "H7-302",
          "description": "tempor nisi consequat. ullamco et exercitation magna incididunt minim elit,. nisi consequat. ullamco et. consequat. ullamco et exercitation magna incididunt. ullamco et exercitation magna incididunt minim elit, aliquip aliqua. Lorem Ut ut. et exercitation magna incididunt minim elit, aliquip aliqua.."
        }
      ],
      "address": "183 Lê Quang Định, phường 9, quận Gò Vấp, thành phố Hồ Chí Minh"
    },
    {
      "id": 11,
      "position": "Y tá",
      "citizenID": "925081736492",
      "firstName": "Minh",
      "lastMiddleName": "Trần Thị",
      "gender": "Nữ",
      "dateOfBirth": "15-09-1970",
      "email": "TranThiM@gmail.com",
      "phoneNum": "0925374819",
      "hometown": "Tràng An, Hoa Lư, Ninh Bình",
      "education": [
        {
          "university": "Trường đại học y dược TP HCM",
          "major": "Khoa Nhi",
          "id": 1,
          "dateBegin": "20-08-1988",
          "dateEnd": "12-07-1994"
        }
      ],
      "cert": [
        {
          "title": "Chứng chỉ hành nghề",
          "Date": "1-10-2018",
          "organization": "Bộ y tế",
          "id": 1
        }
      ],
      "specialty": "Hộ Sinh",
      "schedule": [
        {
          "date": "22-03-2024",
          "timeBegin": "09:00",
          "title": "Kiểm tra và đánh giá bệnh nhân",
          "timeEnd": "11:00",
          "id": 1,
          "room": "H7-302",
          "description": "do adipiscing incididunt amet, ad eiusmod nisi sit sed enim ut quis ipsum. adipiscing incididunt amet, ad. incididunt amet, ad eiusmod nisi sit sed enim ut. amet, ad eiusmod nisi. ad eiusmod nisi sit sed enim ut quis ipsum ea et Lorem magna."
        },
        {
          "date": "25-03-2024 ",
          "timeBegin": "10:30",
          "title": "Điều trị bệnh nhân",
          "timeEnd": "12:30",
          "id": 2,
          "room": "H7-302",
          "description": "dolor aliqua. adipiscing consectetur ipsum. aliqua. adipiscing consectetur ipsum. adipiscing consectetur ipsum ullamco elit, commodo sit Ut minim exercitation nostrud do. consectetur ipsum ullamco elit, commodo sit Ut minim exercitation nostrud do. ipsum ullamco elit, commodo sit."
        },
        {
          "date": "29-03-2024",
          "timeBegin": "10:30",
          "title": "Họp",
          "timeEnd": "12:30",
          "id": 3,
          "room": "H7-302",
          "description": "consectetur minim ipsum dolore eiusmod sit labore ut nostrud exercitation veniam,. minim ipsum dolore eiusmod. ipsum dolore eiusmod sit labore ut nostrud exercitation veniam, enim consequat.. dolore eiusmod sit labore. eiusmod sit labore ut nostrud exercitation veniam, enim."
        }
      ],
      "address": "183 Lê Quang Định, phường 9, quận Gò Vấp, thành phố Hồ Chí Minh"
    },
    {
      "id": 12,
      "position": "Y tá",
      "citizenID": "847129056234",
      "firstName": "Hà",
      "lastMiddleName": "Trần Thị Giang",
      "gender": "Nữ",
      "dateOfBirth": "25-01-1979",
      "email": "TranThiG@gmail.com",
      "phoneNum": "0925748104",
      "hometown": "Bình Nghi, Bình Sơn, Quảng Ngãi",
      "education": [
        {
          "university": "Trường đại học y dược TP HCM",
          "major": "Điều dưỡng",
          "id": 1,
          "dateBegin": "20-08-1997",
          "dateEnd": "12-07-2006"
        }
      ],
      "cert": [
        {
          "title": "Chứng chỉ hành nghề",
          "Date": "1-10-2018",
          "organization": "Bộ y tế",
          "id": 1
        }
      ],
      "specialty": "Điều dưỡng",
      "schedule": [
        {
          "date": "22-03-2024",
          "timeBegin": "09:00",
          "title": "Kiểm tra và đánh giá bệnh nhân",
          "timeEnd": "11:00",
          "id": 1,
          "room": "H7-302",
          "description": "dolore minim ea laboris dolor adipiscing consequat.. minim ea laboris dolor adipiscing. ea laboris dolor adipiscing consequat. enim commodo tempor. laboris dolor adipiscing consequat. enim commodo tempor nostrud aliqua. ad ut. dolor adipiscing consequat. enim commodo tempor nostrud aliqua. ad ut elit, nisi ut."
        },
        {
          "date": "25-03-2024 ",
          "timeBegin": "10:30",
          "title": "Điều trị bệnh nhân",
          "timeEnd": "12:30",
          "id": 2,
          "room": "H7-302",
          "description": "magna commodo nisi amet, sed. commodo nisi amet, sed veniam, ad Lorem ullamco ut exercitation aliqua.. nisi amet, sed veniam, ad Lorem ullamco ut exercitation aliqua. sit aliquip. amet, sed veniam, ad. sed veniam, ad Lorem ullamco ut exercitation aliqua. sit aliquip enim tempor."
        },
        {
          "date": "29-03-2024",
          "timeBegin": "10:30",
          "title": "Họp",
          "timeEnd": "12:30",
          "id": 3,
          "room": "H7-302",
          "description": "amet, nisi commodo consectetur et. nisi commodo consectetur et labore enim incididunt eiusmod sed ad adipiscing nostrud ipsum. commodo consectetur et labore enim incididunt eiusmod sed ad. consectetur et labore enim. et labore enim incididunt eiusmod sed ad adipiscing nostrud ipsum tempor."
        }
      ],
      "address": "183 Lê Quang Định, phường 9, quận Gò Vấp, thành phố Hồ Chí Minh"
    },
    {
      "id": 13,
      "position": "Y tá",
      "citizenID": "681245097836",
      "firstName": "Nhi",
      "lastMiddleName": "Nguyễn Thị",
      "gender": "Nữ",
      "dateOfBirth": "12-10-1979",
      "email": "nguyenThiN@gmail.com",
      "phoneNum": "0934780292",
      "hometown": "An Mỹ, Tuy An, Phú Yên",
      "education": [
        {
          "university": "Trường đại học y dược TP HCM",
          "major": "Điều dưỡng",
          "id": 1,
          "dateBegin": "20-08-1979",
          "dateEnd": "12-07-1985"
        }
      ],
      "cert": [
        {
          "title": "Chứng chỉ hành nghề",
          "Date": "1-10-2018",
          "organization": "Bộ y tế",
          "id": 1
        }
      ],
      "specialty": "Gây mê hồi sức",
      "schedule": [
        {
          "date": "22-03-2024",
          "timeBegin": "09:00",
          "title": "Kiểm tra và đánh giá bệnh nhân",
          "timeEnd": "11:00",
          "id": 1,
          "room": "H7-302",
          "description": "nostrud sed nisi ex magna enim commodo exercitation veniam, ut tempor amet, dolore. sed nisi ex magna enim commodo exercitation veniam, ut tempor. nisi ex magna enim commodo exercitation veniam, ut tempor amet, dolore ullamco. ex magna enim commodo exercitation veniam, ut tempor. magna enim commodo exercitation veniam, ut tempor amet, dolore."
        },
        {
          "date": "25-03-2024 ",
          "timeBegin": "10:30",
          "title": "Điều trị bệnh nhân",
          "timeEnd": "12:30",
          "id": 2,
          "room": "H7-302",
          "description": "consectetur minim et laboris consequat. quis ullamco nisi incididunt ea tempor exercitation ad. minim et laboris consequat. quis. et laboris consequat. quis ullamco. laboris consequat. quis ullamco nisi incididunt ea tempor exercitation ad labore. consequat. quis ullamco nisi incididunt ea tempor exercitation ad labore Lorem dolor elit,."
        },
        {
          "date": "29-03-2024",
          "timeBegin": "10:30",
          "title": "Họp",
          "timeEnd": "12:30",
          "id": 3,
          "room": "H7-302",
          "description": "aliquip nisi incididunt commodo Ut do eiusmod exercitation veniam, adipiscing. nisi incididunt commodo Ut do eiusmod exercitation veniam,. incididunt commodo Ut do eiusmod exercitation veniam, adipiscing. commodo Ut do eiusmod exercitation veniam, adipiscing tempor. Ut do eiusmod exercitation veniam, adipiscing."
        }
      ],
      "address": "183 Lê Quang Định, phường 9, quận Gò Vấp, thành phố Hồ Chí Minh"
    },
    {
      "id": 14,
      "position": "Y tá",
      "citizenID": "530279416785",
      "firstName": "Thảo",
      "lastMiddleName": "Nguyễn Thị",
      "gender": "Nữ",
      "dateOfBirth": "16-10-1989",
      "email": "NguyenThiT@gmail.com",
      "phoneNum": "0977881902",
      "hometown": "Hội An, Tuy Hòa, Phú Yên",
      "education": [
        {
          "university": "Trường đại học y dược TP HCM",
          "major": "Khoa Nhi",
          "id": 1,
          "dateBegin": "20-08-2007",
          "dateEnd": "12-07-2015"
        }
      ],
      "cert": [
        {
          "title": "Chứng chỉ hành nghề",
          "Date": "1-10-2018",
          "organization": "Bộ y tế",
          "id": 1
        }
      ],
      "specialty": "Hộ Sinh",
      "schedule": [
        {
          "date": "22-03-2024",
          "timeBegin": "09:00",
          "title": "Kiểm tra và đánh giá bệnh nhân",
          "timeEnd": "11:00",
          "id": 1,
          "room": "H7-302",
          "description": "minim aliqua. ut Ut nostrud. aliqua. ut Ut nostrud adipiscing veniam, dolore exercitation magna consectetur sit. ut Ut nostrud adipiscing veniam, dolore exercitation magna consectetur sit ad Lorem sed. Ut nostrud adipiscing veniam, dolore exercitation magna consectetur sit. nostrud adipiscing veniam, dolore exercitation magna."
        },
        {
          "date": "25-03-2024 ",
          "timeBegin": "10:30",
          "title": "Điều trị bệnh nhân",
          "timeEnd": "12:30",
          "id": 2,
          "room": "H7-302",
          "description": "elit, enim veniam, dolore. enim veniam, dolore ut amet, ad. veniam, dolore ut amet, ad quis sit Ut. dolore ut amet, ad quis. ut amet, ad quis sit Ut ea nisi dolor."
        },
        {
          "date": "29-03-2024",
          "timeBegin": "10:30",
          "title": "Họp",
          "timeEnd": "12:30",
          "id": 3,
          "room": "H7-302",
          "description": "labore veniam, amet, aliquip et ut ullamco consectetur commodo sed elit, adipiscing. veniam, amet, aliquip et ut ullamco consectetur commodo sed elit, adipiscing nisi sit. amet, aliquip et ut ullamco consectetur commodo sed elit, adipiscing nisi sit. aliquip et ut ullamco consectetur commodo sed elit,. et ut ullamco consectetur commodo sed elit, adipiscing."
        }
      ],
      "address": "183 Lê Quang Định, phường 9, quận Gò Vấp, thành phố Hồ Chí Minh"
    },
    {
      "id": 15,
      "position": "Y tá",
      "citizenID": "490328157642",
      "firstName": "Nhã",
      "lastMiddleName": "Đinh Nguyễn Xuân",
      "gender": "Nam",
      "dateOfBirth": "25-01-1995",
      "email": "DinhNguyenX@gmail.com",
      "phoneNum": "0929384619",
      "hometown": "Bình An, Long Mỹ, Hậu Giang",
      "education": [
        {
          "university": "Trường đại học y dược TP HCM",
          "major": "Điều dưỡng",
          "id": 1,
          "dateBegin": "20-08-2013",
          "dateEnd": "12-07-2018"
        }
      ],
      "cert": [
        {
          "title": "Chứng chỉ hành nghề",
          "Date": "1-10-2018",
          "organization": "Bộ y tế",
          "id": 1
        }
      ],
      "specialty": "Điều dưỡng",
      "schedule": [
        {
          "date": "22-03-2024",
          "timeBegin": "09:00",
          "title": "Kiểm tra và đánh giá bệnh nhân",
          "timeEnd": "11:00",
          "id": 1,
          "room": "H7-302",
          "description": "adipiscing do minim sit. do minim sit Lorem. minim sit Lorem ea aliqua. commodo eiusmod. sit Lorem ea aliqua. commodo eiusmod. Lorem ea aliqua. commodo eiusmod dolor tempor labore ullamco et ipsum magna."
        },
        {
          "date": "25-03-2024 ",
          "timeBegin": "10:30",
          "title": "Điều trị bệnh nhân",
          "timeEnd": "12:30",
          "id": 2,
          "room": "H7-302",
          "description": "Lorem nisi amet, enim ea commodo ut. nisi amet, enim ea commodo ut Ut exercitation magna nostrud. amet, enim ea commodo ut Ut exercitation. enim ea commodo ut Ut exercitation magna nostrud minim. ea commodo ut Ut exercitation."
        },
        {
          "date": "29-03-2024",
          "timeBegin": "10:30",
          "title": "Họp",
          "timeEnd": "12:30",
          "id": 3,
          "room": "H7-302",
          "description": "dolor exercitation tempor nostrud et aliquip ipsum. exercitation tempor nostrud et aliquip ipsum veniam, sit elit, ex. tempor nostrud et aliquip ipsum veniam, sit. nostrud et aliquip ipsum veniam, sit elit, ex Ut magna. et aliquip ipsum veniam, sit elit, ex Ut."
        }
      ],
      "address": "183 Lê Quang Định, phường 9, quận Gò Vấp, thành phố Hồ Chí Minh"
    },
    {
      "id": 16,
      "position": "Y tá",
      "citizenID": "816490235781",
      "firstName": "Hương",
      "lastMiddleName": "Đinh Thị Lan",
      "gender": "Nữ",
      "dateOfBirth": "25-01-1992",
      "email": "DinhThiL@gmail.com",
      "phoneNum": "0900882718",
      "hometown": "An Hòa, Tân Biên, Tây Ninh",
      "education": [
        {
          "university": "Trường đại học y dược TP HCM",
          "major": "Điều dưỡng",
          "id": 1,
          "dateBegin": "20-08-2010",
          "dateEnd": "12-07-2018"
        }
      ],
      "cert": [
        {
          "title": "Chứng chỉ hành nghề",
          "Date": "1-10-2018",
          "organization": "Bộ y tế",
          "id": 1
        }
      ],
      "specialty": "Gây mê hồi sức",
      "schedule": [
        {
          "date": "22-03-2024",
          "timeBegin": "09:00",
          "title": "Kiểm tra và đánh giá bệnh nhân",
          "timeEnd": "11:00",
          "id": 1,
          "room": "H7-302",
          "description": "quis ut ex Lorem amet, aliquip adipiscing. ut ex Lorem amet, aliquip adipiscing ipsum ea Ut minim. ex Lorem amet, aliquip adipiscing ipsum ea Ut minim ut. Lorem amet, aliquip adipiscing. amet, aliquip adipiscing ipsum ea Ut."
        },
        {
          "date": "25-03-2024 ",
          "timeBegin": "10:30",
          "title": "Điều trị bệnh nhân",
          "timeEnd": "12:30",
          "id": 2,
          "room": "H7-302",
          "description": "minim aliquip ad et Ut ea dolor laboris. aliquip ad et Ut ea dolor laboris nostrud sit elit, consectetur Lorem. ad et Ut ea dolor laboris nostrud. et Ut ea dolor laboris nostrud sit elit, consectetur Lorem aliqua. tempor ut. Ut ea dolor laboris nostrud."
        },
        {
          "date": "29-03-2024",
          "timeBegin": "10:30",
          "title": "Họp",
          "timeEnd": "12:30",
          "id": 3,
          "room": "H7-302",
          "description": "amet, do consequat. consectetur tempor. do consequat. consectetur tempor. consequat. consectetur tempor quis ut magna enim ut veniam, incididunt. consectetur tempor quis ut magna enim. tempor quis ut magna enim ut veniam,."
        }
      ],
      "address": "183 Lê Quang Định, phường 9, quận Gò Vấp, thành phố Hồ Chí Minh"
    },
    {
      "id": 17,
      "position": "Y tá",
      "citizenID": "243809517826",
      "firstName": "Nhi",
      "lastMiddleName": "Hà Tuyết",
      "gender": "Nữ",
      "dateOfBirth": "29-02-1988",
      "email": "HaTuyeN@gmail.com",
      "phoneNum": "0915472984",
      "hometown": "Phước Hưng, Đồng Phú, Bình Phước",
      "education": [
        {
          "university": "Trường đại học y dược TP HCM",
          "major": "Khoa Nhi",
          "id": 1,
          "dateBegin": "20-08-2009",
          "dateEnd": "12-07-2015"
        }
      ],
      "cert": [
        {
          "title": "Chứng chỉ hành nghề",
          "Date": "1-10-2018",
          "organization": "Bộ y tế",
          "id": 1
        }
      ],
      "specialty": "Hộ sinh",
      "schedule": [
        {
          "date": "22-03-2024",
          "timeBegin": "09:00",
          "title": "Kiểm tra và đánh giá bệnh nhân",
          "timeEnd": "11:00",
          "id": 1,
          "room": "H7-302",
          "description": "laboris Lorem dolore consectetur aliqua. enim do ullamco ut et. Lorem dolore consectetur aliqua. enim do ullamco ut et tempor incididunt eiusmod minim. dolore consectetur aliqua. enim. consectetur aliqua. enim do. aliqua. enim do ullamco ut et."
        },
        {
          "date": "25-03-2024 ",
          "timeBegin": "10:30",
          "title": "Điều trị bệnh nhân",
          "timeEnd": "12:30",
          "id": 2,
          "room": "H7-302",
          "description": "enim nostrud veniam, minim incididunt consectetur. nostrud veniam, minim incididunt consectetur exercitation ex consequat. adipiscing amet, do. veniam, minim incididunt consectetur exercitation ex consequat. adipiscing amet,. minim incididunt consectetur exercitation ex consequat. adipiscing amet, do nisi. incididunt consectetur exercitation ex consequat.."
        },
        {
          "date": "29-03-2024",
          "timeBegin": "10:30",
          "title": "Họp",
          "timeEnd": "12:30",
          "id": 3,
          "room": "H7-302",
          "description": "aliqua. et ut nostrud consectetur nisi. et ut nostrud consectetur nisi ullamco minim amet, consequat. ea. ut nostrud consectetur nisi. nostrud consectetur nisi ullamco. consectetur nisi ullamco minim amet, consequat. ea."
        }
      ],
      "address": "183 Lê Quang Định, phường 9, quận Gò Vấp, thành phố Hồ Chí Minh"
    },
    {
      "id": 18,
      "position": "Y tá",
      "citizenID": "765024913287",
      "firstName": "Thương",
      "lastMiddleName": "Nguyen Thi",
      "gender": "Nữ",
      "dateOfBirth": "25-01-1994",
      "email": "DinhThiL@gmail.com",
      "phoneNum": "0910284672",
      "hometown": "Hòa Phú, Tân Yên, Bắc Giang",
      "education": [
        {
          "university": "Trường đại học y dược TP HCM",
          "major": "Điều dưỡng",
          "id": 1,
          "dateBegin": "20-08-2012",
          "dateEnd": "12-07-2017"
        }
      ],
      "cert": [
        {
          "title": "Chứng chỉ hành nghề",
          "Date": "1-10-2018",
          "organization": "Bộ y tế",
          "id": 1
        }
      ],
      "specialty": "Điều dưỡng",
      "schedule": [
        {
          "date": "22-03-2024",
          "timeBegin": "09:00",
          "title": "Kiểm tra và đánh giá bệnh nhân",
          "timeEnd": "11:00",
          "id": 1,
          "room": "H7-302",
          "description": "enim labore eiusmod elit, nostrud quis aliquip sit consequat. consectetur ex. labore eiusmod elit, nostrud. eiusmod elit, nostrud quis. elit, nostrud quis aliquip sit consequat. consectetur ex Ut ea tempor ad ipsum. nostrud quis aliquip sit consequat. consectetur ex Ut ea tempor."
        },
        {
          "date": "25-03-2024 ",
          "timeBegin": "10:30",
          "title": "Điều trị bệnh nhân",
          "timeEnd": "12:30",
          "id": 2,
          "room": "H7-302",
          "description": "magna veniam, eiusmod ipsum ullamco consequat. laboris labore do. veniam, eiusmod ipsum ullamco. eiusmod ipsum ullamco consequat. laboris labore do commodo enim minim ut. ipsum ullamco consequat. laboris labore do commodo enim minim ut. ullamco consequat. laboris labore do."
        },
        {
          "date": "29-03-2024",
          "timeBegin": "10:30",
          "title": "Họp",
          "timeEnd": "12:30",
          "id": 3,
          "room": "H7-302",
          "description": "ut do aliquip ea labore tempor. do aliquip ea labore. aliquip ea labore tempor. ea labore tempor et adipiscing consequat. nisi quis enim sit eiusmod elit, Lorem. labore tempor et adipiscing consequat. nisi quis."
        }
      ],
      "address": "183 Lê Quang Định, phường 9, quận Gò Vấp, thành phố Hồ Chí Minh"
    },
    {
      "id": 19,
      "position": "Y tá",
      "citizenID": "978032165794",
      "firstName": "Hòa",
      "lastMiddleName": "Lê Trúc",
      "gender": "Nữ",
      "dateOfBirth": "25-01-1986",
      "email": "LeTrucH@gmail.com",
      "phoneNum": "0947263819",
      "hometown": "Thạch Thắng, Thạch An, Cao Bằng",
      "education": [
        {
          "university": "Trường đại học y dược TP HCM",
          "major": "Điều dưỡng",
          "id": 1,
          "dateBegin": "20-08-2004",
          "dateEnd": "12-07-2009"
        }
      ],
      "cert": [
        {
          "title": "Chứng chỉ hành nghề",
          "Date": "1-10-2018",
          "organization": "Bộ y tế",
          "id": 1
        }
      ],
      "specialty": "Gây mê hồi sức",
      "schedule": [
        {
          "date": "22-03-2024",
          "timeBegin": "09:00",
          "title": "Kiểm tra và đánh giá bệnh nhân",
          "timeEnd": "11:00",
          "id": 1,
          "room": "H7-302",
          "description": "sed eiusmod tempor dolor ipsum sit magna ut quis elit, minim do. eiusmod tempor dolor ipsum sit magna ut. tempor dolor ipsum sit magna ut quis. dolor ipsum sit magna ut quis elit, minim do. ipsum sit magna ut quis elit, minim do veniam,."
        },
        {
          "date": "25-03-2024 ",
          "timeBegin": "10:30",
          "title": "Điều trị bệnh nhân",
          "timeEnd": "12:30",
          "id": 2,
          "room": "H7-302",
          "description": "ex dolor sed adipiscing. dolor sed adipiscing aliqua. Ut. sed adipiscing aliqua. Ut quis incididunt elit,. adipiscing aliqua. Ut quis incididunt elit, dolore ea nostrud ipsum tempor. aliqua. Ut quis incididunt elit, dolore ea nostrud ipsum tempor nisi."
        },
        {
          "date": "29-03-2024",
          "timeBegin": "10:30",
          "title": "Họp",
          "timeEnd": "12:30",
          "id": 3,
          "room": "H7-302",
          "description": "commodo ut Lorem tempor et. ut Lorem tempor et ut ad. Lorem tempor et ut. tempor et ut ad minim. et ut ad minim do eiusmod veniam, enim incididunt."
        }
      ],
      "address": "183 Lê Quang Định, phường 9, quận Gò Vấp, thành phố Hồ Chí Minh"
    },
    {
      "id": 20,
      "position": "Y tá",
      "citizenID": "587401239865",
      "firstName": "Phương",
      "lastMiddleName": "Lê Thị",
      "gender": "Nữ",
      "dateOfBirth": "25-01-1974",
      "email": "LeThiP@gmail.com",
      "phoneNum": "0947281937",
      "hometown": "Lạc Hồng, Thanh Trì, Hà Nội",
      "education": [
        {
          "university": "Trường đại học y dược TP HCM",
          "major": "Khoa Nhi",
          "id": 1,
          "dateBegin": "20-08-1992",
          "dateEnd": "12-07-2000"
        }
      ],
      "cert": [
        {
          "title": "Chứng chỉ hành nghề",
          "Date": "1-10-2018",
          "organization": "Bộ y tế",
          "id": 1
        }
      ],
      "specialty": "Hộ sinh",
      "schedule": [
        {
          "date": "22-03-2024",
          "timeBegin": "09:00",
          "title": "Kiểm tra và đánh giá bệnh nhân",
          "timeEnd": "11:00",
          "id": 1,
          "room": "H7-302",
          "description": "veniam, ex nisi minim Lorem ea sit quis amet, ut. ex nisi minim Lorem. nisi minim Lorem ea sit quis amet, ut eiusmod nostrud incididunt. minim Lorem ea sit quis amet, ut. Lorem ea sit quis amet, ut eiusmod nostrud incididunt consectetur elit, dolor tempor."
        },
        {
          "date": "25-03-2024 ",
          "timeBegin": "10:30",
          "title": "Điều trị bệnh nhân",
          "timeEnd": "12:30",
          "id": 2,
          "room": "H7-302",
          "description": "magna nisi eiusmod Lorem aliqua. adipiscing minim sed exercitation elit, ullamco dolor. nisi eiusmod Lorem aliqua. adipiscing minim sed exercitation elit,. eiusmod Lorem aliqua. adipiscing minim sed exercitation elit, ullamco dolor et ut. Lorem aliqua. adipiscing minim sed exercitation elit,. aliqua. adipiscing minim sed exercitation."
        },
        {
          "date": "29-03-2024",
          "timeBegin": "10:30",
          "title": "Họp",
          "timeEnd": "12:30",
          "id": 3,
          "room": "H7-302",
          "description": "magna ut ipsum nostrud incididunt exercitation. ut ipsum nostrud incididunt exercitation commodo sit. ipsum nostrud incididunt exercitation commodo sit nisi veniam, Lorem ad ea eiusmod. nostrud incididunt exercitation commodo sit nisi veniam, Lorem. incididunt exercitation commodo sit nisi veniam, Lorem ad ea eiusmod et sed labore."
        }
      ],
      "address": "183 Lê Quang Định, phường 9, quận Gò Vấp, thành phố Hồ Chí Minh"
    },
    {
      "id": 21,
      "position": "Nhân viên hỗ trợ",
      "citizenID": "925081736492",
      "firstName": "Minh",
      "lastMiddleName": "Trần Thị",
      "gender": "Nữ",
      "dateOfBirth": "15-09-1970",
      "email": "TranThiM@gmail.com",
      "phoneNum": "0925374819",
      "hometown": "Tràng An, Hoa Lư, Ninh Bình",
      "education": [
        {
          "university": "Trường đại học y dược TP HCM",
          "major": "Khoa Nhi",
          "id": 1,
          "dateBegin": "20-08-1988",
          "dateEnd": "12-07-1994"
        }
      ],
      "cert": [
        {
          "title": "Chứng chỉ hành nghề",
          "Date": "1-10-2018",
          "organization": "Bộ y tế",
          "id": 1
        }
      ],
      "specialty": "Hộ Sinh",
      "schedule": [
        {
          "date": "22-03-2024",
          "timeBegin": "09:00",
          "title": "Kiểm tra và đánh giá bệnh nhân",
          "timeEnd": "11:00",
          "id": 1,
          "room": "H7-302",
          "description": "veniam, elit, et Lorem tempor consectetur consequat. do nostrud. elit, et Lorem tempor consectetur consequat. do nostrud nisi ut adipiscing laboris ea. et Lorem tempor consectetur consequat.. Lorem tempor consectetur consequat. do nostrud nisi ut adipiscing laboris ea. tempor consectetur consequat. do nostrud nisi ut adipiscing laboris."
        },
        {
          "date": "25-03-2024 ",
          "timeBegin": "10:30",
          "title": "Điều trị bệnh nhân",
          "timeEnd": "12:30",
          "id": 2,
          "room": "H7-302",
          "description": "dolore ullamco tempor sed. ullamco tempor sed Ut incididunt consectetur et. tempor sed Ut incididunt consectetur et ipsum consequat. ut aliqua. aliquip do. sed Ut incididunt consectetur et ipsum consequat. ut aliqua. aliquip do. Ut incididunt consectetur et ipsum consequat. ut aliqua. aliquip."
        },
        {
          "date": "29-03-2024",
          "timeBegin": "10:30",
          "title": "Họp",
          "timeEnd": "12:30",
          "id": 3,
          "room": "H7-302",
          "description": "quis et minim nisi ad aliqua. exercitation labore ullamco amet,. et minim nisi ad aliqua.. minim nisi ad aliqua. exercitation labore ullamco amet, sed ea. nisi ad aliqua. exercitation labore ullamco amet, sed ea do commodo ut adipiscing. ad aliqua. exercitation labore ullamco amet, sed ea do commodo."
        }
      ],
      "address": "183 Lê Quang Định, phường 9, quận Gò Vấp, thành phố Hồ Chí Minh"
    },
    {
      "id": 22,
      "position": "Nhân viên hỗ trợ",
      "citizenID": "847129056234",
      "firstName": "Hà",
      "lastMiddleName": "Trần Thị Giang",
      "gender": "Nữ",
      "dateOfBirth": "25-01-1979",
      "email": "TranThiG@gmail.com",
      "phoneNum": "0925748104",
      "hometown": "Bình Nghi, Bình Sơn, Quảng Ngãi",
      "education": [
        {
          "university": "Trường đại học y dược TP HCM",
          "major": "Điều dưỡng",
          "id": 1,
          "dateBegin": "20-08-1997",
          "dateEnd": "12-07-2006"
        }
      ],
      "cert": [
        {
          "title": "Chứng chỉ hành nghề",
          "Date": "1-10-2018",
          "organization": "Bộ y tế",
          "id": 1
        }
      ],
      "specialty": "Điều dưỡng",
      "schedule": [
        {
          "date": "22-03-2024",
          "timeBegin": "09:00",
          "title": "Kiểm tra và đánh giá bệnh nhân",
          "timeEnd": "11:00",
          "id": 1,
          "room": "H7-302",
          "description": "nostrud exercitation ex aliqua.. exercitation ex aliqua. dolor ut Lorem sed labore elit, incididunt Ut. ex aliqua. dolor ut Lorem sed labore elit, incididunt Ut ullamco tempor consequat.. aliqua. dolor ut Lorem sed labore elit, incididunt Ut ullamco tempor consequat. commodo. dolor ut Lorem sed labore elit, incididunt Ut."
        },
        {
          "date": "25-03-2024 ",
          "timeBegin": "10:30",
          "title": "Điều trị bệnh nhân",
          "timeEnd": "12:30",
          "id": 2,
          "room": "H7-302",
          "description": "minim eiusmod et do ex quis commodo elit, ipsum ut sit. eiusmod et do ex quis commodo. et do ex quis commodo elit, ipsum ut sit amet, exercitation consequat.. do ex quis commodo elit,. ex quis commodo elit, ipsum ut sit amet, exercitation consequat.."
        },
        {
          "date": "29-03-2024",
          "timeBegin": "10:30",
          "title": "Họp",
          "timeEnd": "12:30",
          "id": 3,
          "room": "H7-302",
          "description": "enim ut commodo ut et consequat. veniam, amet, magna. ut commodo ut et consequat.. commodo ut et consequat. veniam, amet, magna exercitation do. ut et consequat. veniam, amet, magna exercitation do. et consequat. veniam, amet,."
        }
      ],
      "address": "183 Lê Quang Định, phường 9, quận Gò Vấp, thành phố Hồ Chí Minh"
    },
    {
      "id": 23,
      "position": "Nhân viên hỗ trợ",
      "citizenID": "681245097836",
      "firstName": "Nhi",
      "lastMiddleName": "Nguyễn Thị",
      "gender": "Nữ",
      "dateOfBirth": "12-10-1979",
      "email": "nguyenThiN@gmail.com",
      "phoneNum": "0934780292",
      "hometown": "An Mỹ, Tuy An, Phú Yên",
      "education": [
        {
          "university": "Trường đại học y dược TP HCM",
          "major": "Điều dưỡng",
          "id": 1,
          "dateBegin": "20-08-1979",
          "dateEnd": "12-07-1985"
        }
      ],
      "cert": [
        {
          "title": "Chứng chỉ hành nghề",
          "Date": "1-10-2018",
          "organization": "Bộ y tế",
          "id": 1
        }
      ],
      "specialty": "Gây mê hồi sức",
      "schedule": [
        {
          "date": "22-03-2024",
          "timeBegin": "09:00",
          "title": "Kiểm tra và đánh giá bệnh nhân",
          "timeEnd": "11:00",
          "id": 1,
          "room": "H7-302",
          "description": "ea nostrud amet, ex. nostrud amet, ex veniam, Ut quis tempor aliqua. labore et dolor elit,. amet, ex veniam, Ut quis. ex veniam, Ut quis. veniam, Ut quis tempor aliqua. labore et dolor elit, aliquip commodo sed consequat.."
        },
        {
          "date": "25-03-2024 ",
          "timeBegin": "10:30",
          "title": "Điều trị bệnh nhân",
          "timeEnd": "12:30",
          "id": 2,
          "room": "H7-302",
          "description": "consequat. ullamco do magna ut incididunt. ullamco do magna ut incididunt aliqua. laboris dolor ad aliquip sit. do magna ut incididunt aliqua. laboris dolor ad aliquip sit ut ipsum minim. magna ut incididunt aliqua. laboris dolor ad. ut incididunt aliqua. laboris."
        },
        {
          "date": "29-03-2024",
          "timeBegin": "10:30",
          "title": "Họp",
          "timeEnd": "12:30",
          "id": 3,
          "room": "H7-302",
          "description": "ipsum sed ad labore elit, Lorem minim magna. sed ad labore elit, Lorem minim magna do quis dolore. ad labore elit, Lorem minim magna do quis dolore. labore elit, Lorem minim magna do quis. elit, Lorem minim magna do quis dolore adipiscing."
        }
      ],
      "address": "183 Lê Quang Định, phường 9, quận Gò Vấp, thành phố Hồ Chí Minh"
    },
    {
      "id": 24,
      "position": "Nhân viên hỗ trợ",
      "citizenID": "530279416785",
      "firstName": "Thảo",
      "lastMiddleName": "Nguyễn Thị",
      "gender": "Nữ",
      "dateOfBirth": "16-10-1989",
      "email": "NguyenThiT@gmail.com",
      "phoneNum": "0977881902",
      "hometown": "Hội An, Tuy Hòa, Phú Yên",
      "education": [
        {
          "university": "Trường đại học y dược TP HCM",
          "major": "Khoa Nhi",
          "id": 1,
          "dateBegin": "20-08-2007",
          "dateEnd": "12-07-2015"
        }
      ],
      "cert": [
        {
          "title": "Chứng chỉ hành nghề",
          "Date": "1-10-2018",
          "organization": "Bộ y tế",
          "id": 1
        }
      ],
      "specialty": "Hộ Sinh",
      "schedule": [
        {
          "date": "22-03-2024",
          "timeBegin": "09:00",
          "title": "Kiểm tra và đánh giá bệnh nhân",
          "timeEnd": "11:00",
          "id": 1,
          "room": "H7-302",
          "description": "tempor sed veniam, ipsum sit commodo magna. sed veniam, ipsum sit commodo magna quis. veniam, ipsum sit commodo magna. ipsum sit commodo magna quis adipiscing. sit commodo magna quis."
        },
        {
          "date": "25-03-2024 ",
          "timeBegin": "10:30",
          "title": "Điều trị bệnh nhân",
          "timeEnd": "12:30",
          "id": 2,
          "room": "H7-302",
          "description": "quis consequat. et aliquip minim nostrud sed Ut tempor elit, consectetur ipsum do. consequat. et aliquip minim nostrud sed Ut tempor elit, consectetur ipsum. et aliquip minim nostrud. aliquip minim nostrud sed Ut tempor elit, consectetur ipsum. minim nostrud sed Ut tempor elit, consectetur ipsum do Lorem eiusmod adipiscing magna."
        },
        {
          "date": "29-03-2024",
          "timeBegin": "10:30",
          "title": "Họp",
          "timeEnd": "12:30",
          "id": 3,
          "room": "H7-302",
          "description": "magna incididunt consectetur dolore ipsum nisi commodo amet, enim exercitation. incididunt consectetur dolore ipsum nisi commodo amet, enim exercitation. consectetur dolore ipsum nisi commodo amet,. dolore ipsum nisi commodo amet, enim. ipsum nisi commodo amet, enim exercitation laboris sit."
        }
      ],
      "address": "183 Lê Quang Định, phường 9, quận Gò Vấp, thành phố Hồ Chí Minh"
    },
    {
      "id": 25,
      "position": "Nhân viên hỗ trợ",
      "citizenID": "490328157642",
      "firstName": "Nhã",
      "lastMiddleName": "Đinh Nguyễn Xuân",
      "gender": "Nam",
      "dateOfBirth": "25-01-1995",
      "email": "DinhNguyenX@gmail.com",
      "phoneNum": "0929384619",
      "hometown": "Bình An, Long Mỹ, Hậu Giang",
      "education": [
        {
          "university": "Trường đại học y dược TP HCM",
          "major": "Điều dưỡng",
          "id": 1,
          "dateBegin": "20-08-2013",
          "dateEnd": "12-07-2018"
        }
      ],
      "cert": [
        {
          "title": "Chứng chỉ hành nghề",
          "Date": "1-10-2018",
          "organization": "Bộ y tế",
          "id": 1
        }
      ],
      "specialty": "Điều dưỡng",
      "schedule": [
        {
          "date": "22-03-2024",
          "timeBegin": "09:00",
          "title": "Kiểm tra và đánh giá bệnh nhân",
          "timeEnd": "11:00",
          "id": 1,
          "room": "H7-302",
          "description": "Ut sit commodo tempor consequat. eiusmod nisi. sit commodo tempor consequat.. commodo tempor consequat. eiusmod nisi quis. tempor consequat. eiusmod nisi quis. consequat. eiusmod nisi quis sed laboris adipiscing Lorem dolore."
        },
        {
          "date": "25-03-2024 ",
          "timeBegin": "10:30",
          "title": "Điều trị bệnh nhân",
          "timeEnd": "12:30",
          "id": 2,
          "room": "H7-302",
          "description": "dolore consequat. quis veniam, dolor ut ipsum. consequat. quis veniam, dolor ut. quis veniam, dolor ut ipsum eiusmod consectetur Lorem. veniam, dolor ut ipsum eiusmod consectetur Lorem do aliqua. nostrud incididunt enim. dolor ut ipsum eiusmod consectetur Lorem."
        },
        {
          "date": "29-03-2024",
          "timeBegin": "10:30",
          "title": "Họp",
          "timeEnd": "12:30",
          "id": 3,
          "room": "H7-302",
          "description": "ut labore eiusmod nostrud adipiscing elit, veniam, nisi. labore eiusmod nostrud adipiscing elit, veniam, nisi. eiusmod nostrud adipiscing elit, veniam, nisi commodo sit et magna quis aliquip. nostrud adipiscing elit, veniam, nisi commodo sit. adipiscing elit, veniam, nisi commodo sit et magna quis aliquip aliqua. ad."
        }
      ],
      "address": "183 Lê Quang Định, phường 9, quận Gò Vấp, thành phố Hồ Chí Minh"
    },
    {
      "id": 26,
      "position": "Nhân viên hỗ trợ",
      "citizenID": "816490235781",
      "firstName": "Hương",
      "lastMiddleName": "Đinh Thị Lan",
      "gender": "Nữ",
      "dateOfBirth": "25-01-1992",
      "email": "DinhThiL@gmail.com",
      "phoneNum": "0900882718",
      "hometown": "An Hòa, Tân Biên, Tây Ninh",
      "education": [
        {
          "university": "Trường đại học y dược TP HCM",
          "major": "Điều dưỡng",
          "id": 1,
          "dateBegin": "20-08-2010",
          "dateEnd": "12-07-2018"
        }
      ],
      "cert": [
        {
          "title": "Chứng chỉ hành nghề",
          "Date": "1-10-2018",
          "organization": "Bộ y tế",
          "id": 1
        }
      ],
      "specialty": "Gây mê hồi sức",
      "schedule": [
        {
          "date": "22-03-2024",
          "timeBegin": "09:00",
          "title": "Kiểm tra và đánh giá bệnh nhân",
          "timeEnd": "11:00",
          "id": 1,
          "room": "H7-302",
          "description": "enim sit laboris ut. sit laboris ut ex minim sed commodo ad magna ut. laboris ut ex minim sed commodo ad magna. ut ex minim sed commodo ad magna. ex minim sed commodo ad magna ut do dolor nisi aliqua.."
        },
        {
          "date": "25-03-2024 ",
          "timeBegin": "10:30",
          "title": "Điều trị bệnh nhân",
          "timeEnd": "12:30",
          "id": 2,
          "room": "H7-302",
          "description": "sed eiusmod do et nostrud quis ut adipiscing labore minim ipsum commodo. eiusmod do et nostrud quis ut adipiscing labore minim ipsum commodo. do et nostrud quis ut adipiscing. et nostrud quis ut adipiscing labore minim ipsum. nostrud quis ut adipiscing labore minim ipsum commodo nisi amet, ut elit,."
        },
        {
          "date": "29-03-2024",
          "timeBegin": "10:30",
          "title": "Họp",
          "timeEnd": "12:30",
          "id": 3,
          "room": "H7-302",
          "description": "magna aliquip commodo et sed dolore exercitation veniam, laboris. aliquip commodo et sed. commodo et sed dolore. et sed dolore exercitation veniam, laboris consequat. do labore quis ut ullamco. sed dolore exercitation veniam, laboris consequat. do labore quis ut ullamco."
        }
      ],
      "address": "183 Lê Quang Định, phường 9, quận Gò Vấp, thành phố Hồ Chí Minh"
    },
    {
      "id": 27,
      "position": "Nhân viên hỗ trợ",
      "citizenID": "243809517826",
      "firstName": "Nhi",
      "lastMiddleName": "Hà Tuyết",
      "gender": "Nữ",
      "dateOfBirth": "29-02-1988",
      "email": "HaTuyeN@gmail.com",
      "phoneNum": "0915472984",
      "hometown": "Phước Hưng, Đồng Phú, Bình Phước",
      "education": [
        {
          "university": "Trường đại học y dược TP HCM",
          "major": "Khoa Nhi",
          "id": 1,
          "dateBegin": "20-08-2009",
          "dateEnd": "12-07-2015"
        }
      ],
      "cert": [
        {
          "title": "Chứng chỉ hành nghề",
          "Date": "1-10-2018",
          "organization": "Bộ y tế",
          "id": 1
        }
      ],
      "specialty": "Hộ sinh",
      "schedule": [
        {
          "date": "22-03-2024",
          "timeBegin": "09:00",
          "title": "Kiểm tra và đánh giá bệnh nhân",
          "timeEnd": "11:00",
          "id": 1,
          "room": "H7-302",
          "description": "aliquip magna elit, amet, nostrud sit nisi. magna elit, amet, nostrud sit nisi exercitation labore enim. elit, amet, nostrud sit nisi exercitation labore enim ipsum commodo dolor eiusmod ex. amet, nostrud sit nisi exercitation labore enim. nostrud sit nisi exercitation."
        },
        {
          "date": "25-03-2024 ",
          "timeBegin": "10:30",
          "title": "Điều trị bệnh nhân",
          "timeEnd": "12:30",
          "id": 2,
          "room": "H7-302",
          "description": "consequat. ea Ut ullamco labore commodo aliqua. ipsum minim amet, veniam,. ea Ut ullamco labore commodo. Ut ullamco labore commodo aliqua.. ullamco labore commodo aliqua. ipsum minim. labore commodo aliqua. ipsum minim amet, veniam, incididunt sed quis ad tempor."
        },
        {
          "date": "29-03-2024",
          "timeBegin": "10:30",
          "title": "Họp",
          "timeEnd": "12:30",
          "id": 3,
          "room": "H7-302",
          "description": "tempor Lorem ut aliqua. enim exercitation nisi magna sit. Lorem ut aliqua. enim exercitation nisi magna sit ea. ut aliqua. enim exercitation nisi magna sit. aliqua. enim exercitation nisi magna sit ea amet, elit,. enim exercitation nisi magna sit ea amet, elit, nostrud Ut et."
        }
      ],
      "address": "183 Lê Quang Định, phường 9, quận Gò Vấp, thành phố Hồ Chí Minh"
    },
    {
      "id": 28,
      "position": "Nhân viên hỗ trợ",
      "citizenID": "765024913287",
      "firstName": "Thương",
      "lastMiddleName": "Nguyen Thi",
      "gender": "Nữ",
      "dateOfBirth": "25-01-1994",
      "email": "DinhThiL@gmail.com",
      "phoneNum": "0910284672",
      "hometown": "Hòa Phú, Tân Yên, Bắc Giang",
      "education": [
        {
          "university": "Trường đại học y dược TP HCM",
          "major": "Điều dưỡng",
          "id": 1,
          "dateBegin": "20-08-2012",
          "dateEnd": "12-07-2017"
        }
      ],
      "cert": [
        {
          "title": "Chứng chỉ hành nghề",
          "Date": "1-10-2018",
          "organization": "Bộ y tế",
          "id": 1
        }
      ],
      "specialty": "Điều dưỡng",
      "schedule": [
        {
          "date": "22-03-2024",
          "timeBegin": "09:00",
          "title": "Kiểm tra và đánh giá bệnh nhân",
          "timeEnd": "11:00",
          "id": 1,
          "room": "H7-302",
          "description": "Lorem ex sit enim consequat.. ex sit enim consequat. laboris ad. sit enim consequat. laboris ad incididunt adipiscing labore ea. enim consequat. laboris ad incididunt adipiscing labore ea elit, amet, et sed quis. consequat. laboris ad incididunt adipiscing labore."
        },
        {
          "date": "25-03-2024 ",
          "timeBegin": "10:30",
          "title": "Điều trị bệnh nhân",
          "timeEnd": "12:30",
          "id": 2,
          "room": "H7-302",
          "description": "nostrud ea veniam, ex incididunt ut tempor amet, sit. ea veniam, ex incididunt ut tempor amet, sit minim laboris. veniam, ex incididunt ut tempor amet, sit minim laboris. ex incididunt ut tempor amet, sit minim laboris sed dolor magna exercitation aliqua.. incididunt ut tempor amet, sit minim laboris sed dolor."
        },
        {
          "date": "29-03-2024",
          "timeBegin": "10:30",
          "title": "Họp",
          "timeEnd": "12:30",
          "id": 3,
          "room": "H7-302",
          "description": "dolore Ut sed aliqua. ut. Ut sed aliqua. ut. sed aliqua. ut et dolor. aliqua. ut et dolor consequat. eiusmod. ut et dolor consequat. eiusmod Lorem nostrud aliquip sit."
        }
      ],
      "address": "183 Lê Quang Định, phường 9, quận Gò Vấp, thành phố Hồ Chí Minh"
    },
    {
      "id": 29,
      "position": "Nhân viên hỗ trợ",
      "citizenID": "978032165794",
      "firstName": "Hòa",
      "lastMiddleName": "Lê Trúc",
      "gender": "Nữ",
      "dateOfBirth": "25-01-1986",
      "email": "LeTrucH@gmail.com",
      "phoneNum": "0947263819",
      "hometown": "Thạch Thắng, Thạch An, Cao Bằng",
      "education": [
        {
          "university": "Trường đại học y dược TP HCM",
          "major": "Điều dưỡng",
          "id": 1,
          "dateBegin": "20-08-2004",
          "dateEnd": "12-07-2009"
        }
      ],
      "cert": [
        {
          "title": "Chứng chỉ hành nghề",
          "Date": "1-10-2018",
          "organization": "Bộ y tế",
          "id": 1
        }
      ],
      "specialty": "Gây mê hồi sức",
      "schedule": [
        {
          "date": "22-03-2024",
          "timeBegin": "09:00",
          "title": "Kiểm tra và đánh giá bệnh nhân",
          "timeEnd": "11:00",
          "id": 1,
          "room": "H7-302",
          "description": "Ut labore exercitation ad enim ex dolor do magna et. labore exercitation ad enim ex dolor do. exercitation ad enim ex dolor do magna et ea eiusmod Lorem quis minim. ad enim ex dolor do magna. enim ex dolor do magna et ea eiusmod Lorem quis minim commodo."
        },
        {
          "date": "25-03-2024 ",
          "timeBegin": "10:30",
          "title": "Điều trị bệnh nhân",
          "timeEnd": "12:30",
          "id": 2,
          "room": "H7-302",
          "description": "dolor do consectetur commodo ex elit, eiusmod magna dolore adipiscing aliquip et sed. do consectetur commodo ex elit, eiusmod magna dolore adipiscing. consectetur commodo ex elit, eiusmod magna dolore adipiscing aliquip et sed ea. commodo ex elit, eiusmod magna dolore adipiscing aliquip et sed. ex elit, eiusmod magna dolore adipiscing aliquip et sed ea Ut enim ipsum."
        },
        {
          "date": "29-03-2024",
          "timeBegin": "10:30",
          "title": "Họp",
          "timeEnd": "12:30",
          "id": 3,
          "room": "H7-302",
          "description": "aliqua. consectetur eiusmod laboris tempor consequat.. consectetur eiusmod laboris tempor consequat. veniam, do elit, exercitation aliquip. eiusmod laboris tempor consequat. veniam, do elit, exercitation aliquip. laboris tempor consequat. veniam, do elit,. tempor consequat. veniam, do elit, exercitation."
        }
      ],
      "address": "183 Lê Quang Định, phường 9, quận Gò Vấp, thành phố Hồ Chí Minh"
    },
    {
      "id": 30,
      "position": "Nhân viên hỗ trợ",
      "citizenID": "587401239865",
      "firstName": "Phương",
      "lastMiddleName": "Lê Thị",
      "gender": "Nữ",
      "dateOfBirth": "25-01-1974",
      "email": "LeThiP@gmail.com",
      "phoneNum": "0947281937",
      "hometown": "Lạc Hồng, Thanh Trì, Hà Nội",
      "education": [
        {
          "university": "Trường đại học y dược TP HCM",
          "major": "Khoa Nhi",
          "id": 1,
          "dateBegin": "20-08-1992",
          "dateEnd": "12-07-2000"
        }
      ],
      "cert": [
        {
          "title": "Chứng chỉ hành nghề",
          "Date": "1-10-2018",
          "organization": "Bộ y tế",
          "id": 1
        }
      ],
      "specialty": "Hộ sinh",
      "schedule": [
        {
          "date": "22-03-2024",
          "timeBegin": "09:00",
          "title": "Kiểm tra và đánh giá bệnh nhân",
          "timeEnd": "11:00",
          "id": 1,
          "room": "H7-302",
          "description": "do ipsum nisi aliquip ea. ipsum nisi aliquip ea veniam, quis ut exercitation amet, aliqua. et. nisi aliquip ea veniam, quis ut exercitation amet,. aliquip ea veniam, quis ut exercitation amet, aliqua.. ea veniam, quis ut exercitation amet, aliqua.."
        },
        {
          "date": "25-03-2024 ",
          "timeBegin": "10:30",
          "title": "Điều trị bệnh nhân",
          "timeEnd": "12:30",
          "id": 2,
          "room": "H7-302",
          "description": "nisi tempor et dolore adipiscing incididunt aliquip. tempor et dolore adipiscing incididunt aliquip. et dolore adipiscing incididunt aliquip veniam, elit, enim consectetur nostrud. dolore adipiscing incididunt aliquip veniam, elit, enim consectetur nostrud ex. adipiscing incididunt aliquip veniam, elit, enim consectetur nostrud ex laboris."
        },
        {
          "date": "29-03-2024",
          "timeBegin": "10:30",
          "title": "Họp",
          "timeEnd": "12:30",
          "id": 3,
          "room": "H7-302",
          "description": "amet, enim adipiscing laboris Lorem nisi Ut nostrud veniam, ea. enim adipiscing laboris Lorem nisi Ut nostrud veniam,. adipiscing laboris Lorem nisi. laboris Lorem nisi Ut nostrud veniam, ea elit,. Lorem nisi Ut nostrud veniam, ea elit, aliquip consectetur labore."
        }
      ],
      "address": "183 Lê Quang Định, phường 9, quận Gò Vấp, thành phố Hồ Chí Minh"
    }
  ],
  "Medicine": [
    {
      "id": 1,
      "name": "Paracetamol",
      "departureTime": "07:00",
      "expireDate": "05-12-2029",
      "amount": "10000",
      "arrivalDate": "25-03-2024",
      "arrivalTime": "09:00",
      "departureDate": "01-04-2024"
    },
    {
      "id": 2,
      "name": "Aspirin",
      "departureTime": "07:00",
      "expireDate": "04-10-2029",
      "amount": "10000",
      "arrivalDate": "25-03-2024",
      "arrivalTime": "09:00",
      "departureDate": "01-04-2024"
    },
    {
      "id": 3,
      "name": "Phosphalugel",
      "departureTime": "07:00",
      "expireDate": "02-03-2029",
      "amount": "5000",
      "arrivalDate": "25-03-2024",
      "arrivalTime": "09:00",
      "departureDate": "01-04-2024"
    },
    {
      "id": 4,
      "name": "Ibuprofen",
      "departureTime": "07:00",
      "expireDate": "15-04-2024",
      "amount": "2000",
      "arrivalDate": "25-03-2024",
      "arrivalTime": "09:00",
      "departureDate": "01-04-2024"
    },
    {
      "id": 5,
      "name": "Diphenoxylate",
      "departureTime": "10:00",
      "expireDate": "10-11-2028",
      "amount": "0",
      "arrivalDate": "30-01-2024",
      "arrivalTime": "15:00",
      "departureDate": "12-02-2024"
    },
    {
      "id": 6,
      "name": "Chloramphenicol",
      "departureTime": "14:00",
      "expireDate": "10-11-2028",
      "amount": "2500",
      "arrivalDate": "03-01-2024",
      "arrivalTime": "08:00",
      "departureDate": "17-07-2024"
    },
    {
      "id": 7,
      "name": "Thiamphenicol",
      "departureTime": "13:00",
      "expireDate": "10-11-2028",
      "amount": "2500",
      "arrivalDate": "03-01-2024",
      "arrivalTime": "08:00",
      "departureDate": "17-07-2024"
    },
    {
      "id": 8,
      "name": "Heparin",
      "departureTime": "13:00",
      "expireDate": "02-11-2028",
      "amount": "3500",
      "arrivalDate": "05-05-2024",
      "arrivalTime": "8:00",
      "departureDate": "07-07-2024"
    },
    {
      "id": 10,
      "name": "Acetylcystein",
      "departureTime": "07:00",
      "expireDate": "19-08-2027",
      "amount": "8000",
      "arrivalDate": "15-03-2024",
      "arrivalTime": "15:00",
      "departureDate": "20-03-2024"
    }
  ],
  "Equipment": [
    {
      "id": 1,
      "name": "Máy siêu âm",
      "usageHistory": [
        {
          "room": "Phòng siêu âm số 01",
          "id": 1,
          "date": "27-03-2024",
          "time": "09:00"
        },
        {
          "room": "Phòng siêu âm số 01",
          "id": 2,
          "date": "30-03-2024",
          "time": "11:00"
        }
      ],
      "regularMaintenance": [
        {
          "id": 1,
          "date": "10-01-2023",
          "description": "Cập nhập thêm chức năng"
        },
        {
          "id": 2,
          "date": "10-07-2023",
          "description": "Bảo trì"
        },
        {
          "id": 3,
          "date": "10-01-2024",
          "description": "Nâng cấp chất liệu"
        },
        {
          "id": 4,
          "date": "10-07-2024",
          "description": "Bảo trì"
        }
      ]
    },
    {
      "id": 2,
      "name": "Máy đo điện tâm đồ",
      "usageHistory": [
        {
          "room": "Phòng tim mạch 07",
          "id": 1,
          "date": "21-03-2024",
          "time": "09:00"
        },
        {
          "room": "Phòng tim mạch số 01",
          "id": 2,
          "date": "21-03-2024",
          "time": "11:00"
        },
        {
          "room": "Phòng tim mạch 07",
          "id": 3,
          "date": "22-03-2024",
          "time": "09:00"
        }
      ],
      "regularMaintenance": [
        {
          "id": 1,
          "date": "10-01-2023",
          "description": "Cập nhập thêm chức năng"
        },
        {
          "id": 2,
          "date": "10-07-2023",
          "description": "Bảo trì"
        },
        {
          "id": 3,
          "date": "10-01-2024",
          "description": "Nâng cấp chất liệu"
        },
        {
          "id": 4,
          "date": "10-07-2024",
          "description": "Bảo trì"
        }
      ]
    },
    {
      "id": 3,
      "name": "Máy chụp CT Scan",
      "usageHistory": [
        {
          "room": "Phòng chụp CT số 01",
          "id": 1,
          "date": "23-03-2024",
          "time": "08:00"
        },
        {
          "room": "Phòng chụp CT số 01",
          "id": 2,
          "date": "23-03-2024",
          "time": "11:00"
        },
        {
          "room": "Phòng chụp CT số 01",
          "id": 3,
          "date": "24-03-2024",
          "time": "15:00"
        },
        {
          "room": "Phòng chụp CT số 02",
          "id": 4,
          "date": "24-03-2024",
          "time": "15:00"
        }
      ],
      "regularMaintenance": [
        {
          "id": 1,
          "date": "10-01-2023",
          "description": "Cập nhập thêm chức năng"
        },
        {
          "id": 2,
          "date": "10-07-2023",
          "description": "Bảo trì"
        },
        {
          "id": 3,
          "date": "10-01-2024",
          "description": "Nâng cấp chất liệu"
        },
        {
          "id": 4,
          "date": "10-07-2024",
          "description": "Bảo trì"
        }
      ]
    },
    {
      "id": 4,
      "name": "Máy thở y tế",
      "usageHistory": [
        {
          "room": "Phòng hồi sức cấp cứu số 01",
          "id": 1,
          "date": "22-03-2024",
          "time": "21:00"
        },
        {
          "room": "Phòng hồi sức cấp cứu số 01",
          "id": 2,
          "date": "22-03-2024",
          "time": "11:00"
        }
      ],
      "regularMaintenance": [
        {
          "id": 1,
          "date": "10-01-2023",
          "description": "Cập nhập thêm chức năng"
        },
        {
          "id": 2,
          "date": "10-07-2023",
          "description": "Bảo trì"
        },
        {
          "id": 3,
          "date": "10-01-2024",
          "description": "Nâng cấp chất liệu"
        },
        {
          "id": 4,
          "date": "10-07-2024",
          "description": "Bảo trì"
        }
      ]
    },
    {
      "id": 5,
      "name": "Máy lọc máu",
      "usageHistory": [
        {
          "room": "Phòng cấp cứu số 01",
          "id": 1,
          "date": "19-04-2024",
          "time": "07:00"
        },
        {
          "room": "Phòng cấp cứu số 01",
          "id": 2,
          "date": "20-04-2024",
          "time": "11:00"
        },
        {
          "room": "Phòng cấp cứu số 03",
          "id": 3,
          "date": "20-04-2024",
          "time": "15:00"
        }
      ],
      "regularMaintenance": [
        {
          "id": 1,
          "date": "10-01-2023",
          "description": "Cập nhập thêm chức năng"
        },
        {
          "id": 2,
          "date": "10-07-2023",
          "description": "Bảo trì"
        },
        {
          "id": 3,
          "date": "10-01-2024",
          "description": "Nâng cấp chất liệu"
        },
        {
          "id": 4,
          "date": "10-07-2024",
          "description": "Bảo trì"
        }
      ]
    },
    {
      "id": 6,
      "name": "Máy lọc thận",
      "usageHistory": [
        {
          "room": "Phòng cấp cứu số 01",
          "id": 1,
          "date": "25-05-2024",
          "time": "09:00"
        }
      ],
      "regularMaintenance": [
        {
          "id": 1,
          "date": "10-01-2023",
          "description": "Cập nhập thêm chức năng"
        },
        {
          "id": 2,
          "date": "10-07-2023",
          "description": "Bảo trì"
        },
        {
          "id": 3,
          "date": "10-01-2024",
          "description": "Nâng cấp chất liệu"
        },
        {
          "id": 4,
          "date": "10-07-2024",
          "description": "Bảo trì"
        }
      ]
    },
    {
      "id": 7,
      "name": "Giường cho bệnh nhân",
      "usageHistory": [
        {
          "room": "Phòng hồi sức số 01",
          "id": 1,
          "date": "22-08-2024",
          "time": "09:00"
        },
        {
          "room": "Phòng hồi sức số 02",
          "id": 2,
          "date": "22-08-2024",
          "time": "09:00"
        },
        {
          "room": "Phòng hồi sức số 02",
          "id": 3,
          "date": "22-08-2024",
          "time": "11:00"
        },
        {
          "room": "Phòng hồi sức số 03",
          "id": 4,
          "date": "22-08-2024",
          "time": "11:00"
        },
        {
          "room": "Phòng hồi sức số 01",
          "id": 5,
          "date": "23-08-2024",
          "time": "12:00"
        },
        {
          "room": "Phòng hồi sức số 01",
          "id": 6,
          "date": "23-08-2024",
          "time": "15:00"
        }
      ],
      "regularMaintenance": [
        {
          "id": 1,
          "date": "10-01-2023",
          "description": "Cập nhập thêm chức năng"
        },
        {
          "id": 2,
          "date": "10-07-2023",
          "description": "Bảo trì"
        },
        {
          "id": 3,
          "date": "10-01-2024",
          "description": "Nâng cấp chất liệu"
        },
        {
          "id": 4,
          "date": "10-07-2024",
          "description": "Bảo trì"
        }
      ]
    },
    {
      "id": 8,
      "name": "Máy chụp X-quang",
      "usageHistory": [
        {
          "room": "Phòng chụp X-quang",
          "id": 1,
          "date": "02-02-2024",
          "time": "08:00"
        },
        {
          "room": " Phòng chụp X-quang ",
          "id": 2,
          "date": "02-02-2024",
          "time": "10:00"
        }
      ],
      "regularMaintenance": [
        {
          "id": 1,
          "date": "10-01-2023",
          "description": "Cập nhập thêm chức năng"
        },
        {
          "id": 2,
          "date": "10-07-2023",
          "description": "Bảo trì"
        },
        {
          "id": 3,
          "date": "10-01-2024",
          "description": "Nâng cấp chất liệu"
        },
        {
          "id": 4,
          "date": "10-07-2024",
          "description": "Bảo trì"
        }
      ]
    },
    {
      "id": 9,
      "name": "Máy tim phổi",
      "usageHistory": [
        {
          "room": "Phòng cấp cứu số 01",
          "id": 1,
          "date": "30-04-2024",
          "time": "00:00"
        },
        {
          "room": "Phòng siêu âm số 03",
          "id": 2,
          "date": "30-04-2024",
          "time": "01:00"
        },
        {
          "room": "Phòng siêu âm số 01",
          "id": 3,
          "date": "2-05-2024",
          "time": "22:00"
        }
      ],
      "regularMaintenance": [
        {
          "id": 1,
          "date": "10-01-2023",
          "description": "Cập nhập thêm chức năng"
        },
        {
          "id": 2,
          "date": "10-07-2023",
          "description": "Bảo trì"
        },
        {
          "id": 3,
          "date": "10-01-2024",
          "description": "Nâng cấp chất liệu"
        },
        {
          "id": 4,
          "date": "10-07-2024",
          "description": "Bảo trì"
        }
      ]
    },
    {
      "id": 10,
      "name": "Máy laze y tế",
      "usageHistory": [
        {
          "room": "Phòng cấp mổ 01",
          "id": 1,
          "date": "27-04-2024",
          "time": "00:00"
        },
        {
          "room": "Phòng mổ số 01",
          "id": 2,
          "date": "30-04-2024",
          "time": "01:00"
        }
      ],
      "regularMaintenance": [
        {
          "id": 1,
          "date": "10-01-2023",
          "description": "Cập nhập thêm chức năng"
        },
        {
          "id": 2,
          "date": "10-07-2023",
          "description": "Bảo trì"
        },
        {
          "id": 3,
          "date": "10-01-2024",
          "description": "Nâng cấp chất liệu"
        },
        {
          "id": 4,
          "date": "10-07-2024",
          "description": "Bảo trì"
        }
      ]
    }
  ]
}